Workbook

Sheet README
A1: Texas Instruments Incorporated — Three-Statement Model and DCF
A3: WHAT THIS IS
A4: Scope | B4: Historical FY2021-FY2025 income statement, balance sheet and cash flow, a five-year forecast to FY2030, and a discounted cash flow valuation. Every number in the forecast is a live formula driven from the Assumptions tab.
A5: Source | B5: lab05_financials.json — annual XBRL company facts from the SEC companyfacts API for CIK 97476, taken from Form 10-K filings. FY2023, FY2024 and FY2025 come from the FY2025 10-K, accession 0000097476-26-000059, filed 2026-02-06. No data from any other source has been used.
A6: Units | B6: $ in millions unless stated. Share counts in millions. Per-share figures in dollars.
A8: HOW TO DRIVE IT
A9: 1 | B9: Open the Assumptions tab. The yellow-filled blue cells in columns G to K are the only forecast inputs. Historical columns beside them are live formulas showing the actual ratio, so each assumption can be read against what the business did.
A10: 2 | B10: Open the DCF tab. Cost of capital and terminal assumptions are the blue cells at the top. Type a live share price into the yellow cell to get the upside line and the implied market multiple.
A11: 3 | B11: Check the Checks tab. Every integrity test should read OK. The sanity flags are judgement calls, not errors.
A13: COLOUR CONVENTION
A14: Blue | B14: Hardcoded input or scenario lever.
A15: Black | B15: Formula calculated on that sheet.
A16: Green | B16: Link to another sheet in this workbook.
A17: Yellow fill | B17: Key assumption, or a cell you need to fill in.
A19: WHAT THE HISTORY SHOWS
A20: The cycle | B20: Revenue peaked at $20.0bn in FY2022, fell 12.5% and then 10.7% through the analog downcycle, and recovered 13.0% to $17.7bn in FY2025 — still below the FY2022 peak.
A21: The capex programme | B21: Capital expenditure ran at 4-7% of revenue before 2021 and at 26-31% in FY2023-FY2025. Net PP&E went from $3.3bn to $12.3bn in five years.
A22: The margin cost | B22: Gross margin fell from 68.8% to 57.0% and operating margin from 50.6% to 34.1%, as depreciation on under-utilised new capacity landed in cost of revenue. D&A nearly trebled from $755m to $1,918m and is still climbing.
A23: The funding | B23: Free cash flow fell from $6.3bn to $1.3-2.6bn while distributions continued. Total debt rose from $6.8bn to $14.0bn and buybacks were largely suspended — the diluted share count fell only 0.6% a year against 2-3% a year before 2021.
A24: Working capital | B24: Days of inventory went from 117 to 253 and eased back to 231. That is roughly $2.9bn of cash absorbed since FY2021.
A26: THE CENTRAL JUDGEMENT
B27: The forecast assumes the cycle turns and capital intensity normalises: revenue compounding at about 7% a year, gross margin recovering from 57.0% to 62.0% but NOT back to the 68.8% peak, and capex falling from 25.7% to 12.0% of revenue. That combination is what produces the free cash flow recovery, and it is where the valuation is won or lost. If capex stays near 20% of revenue, or gross margin stalls near 58%, the answer is materially lower. The sensitivity grids on the DCF tab flex cost of capital and the terminal assumption, not these two operating drivers — flex those directly on the Assumptions tab.
A29: KNOWN LIMITATIONS
A30: Not reported | B30: Dividends, buybacks, stock compensation, deferred taxes and the investing section other than capex are absent from the extract. Historical financing and investing totals in this workbook are derived, not as-reported. See the Checks tab for the full list of eleven data-quality flags.
A31: No market data | B31: There is no share price, market capitalisation, credit spread or peer multiple in the source. Cost of capital inputs and the capital structure weights are standard assumptions, not calibrated to TI market data.
A32: Cash is the plug | B32: There is no revolver. If assumed distributions exceed cash generation, the modelled cash balance simply falls, and the Checks tab flags it. The $3.8bn short-term investment portfolio is held flat rather than drawn, which makes the modelled cash trough conservative.
A34: BUILT
A35: Prepared | B35: 15 August 2026, from lab05_financials.json. Formulas are live throughout — no pasted values in any calculated cell.

Sheet Assumptions
A1: Assumptions and Operating Drivers
A2: BLUE cells in the FY2026E–FY2030E columns are the only inputs that drive the forecast. Historical columns are live formulas showing the actual ratio, so you can see each assumption against what the business did.
A4: ($ in millions, except per-share) | B4: FY2021A | C4: FY2022A | D4: FY2023A | E4: FY2024A | F4: FY2025A | G4: FY2026E | H4: FY2027E | I4: FY2028E | J4: FY2029E | K4: FY2030E | M4: Notes / source
A5: REVENUE AND MARGIN
A6: Revenue growth % | B6: n/a | C6: ='Source Data'!C$7/'Source Data'!B$7-1 -> 0.091801134 | D6: ='Source Data'!D$7/'Source Data'!C$7-1 -> -0.12527462 | E6: ='Source Data'!E$7/'Source Data'!D$7-1 -> -0.1071979 | F6: ='Source Data'!F$7/'Source Data'!E$7-1 -> 0.13049038 | G6: 0.1 | H6: 0.08 | I6: 0.07 | J6: 0.06 | K6: 0.05 | M6: FY2023–24 was the analog downcycle (-12.5%, -10.7%); FY2025 recovered +13.0%. Assumes the recovery continues then fades to trend.
A7: Gross margin % | B7: ='Source Data'!B$9/'Source Data'!B$7 -> 0.67466201 | C7: ='Source Data'!C$9/'Source Data'!C$7 -> 0.68758738 | D7: ='Source Data'!D$9/'Source Data'!D$7 -> 0.62897426 | E7: ='Source Data'!E$9/'Source Data'!E$7 -> 0.58142063 | F7: ='Source Data'!F$9/'Source Data'!F$7 -> 0.57024092 | G7: 0.58 | H7: 0.6 | I7: 0.61 | J7: 0.615 | K7: 0.62 | M7: Fell 68.8% -> 57.0% as under-utilised new 300mm capacity depreciates into COGS. Assumes partial recovery on utilisation; NOT a return to the 68% peak, because the depreciation step-up is structural.
A8: R&D % of revenue | B8: ='Source Data'!B$10/'Source Data'!B$7 -> 0.084714348 | C8: ='Source Data'!C$10/'Source Data'!C$7 -> 0.083383263 | D8: ='Source Data'!D$10/'Source Data'!D$7 -> 0.10634169 | E8: ='Source Data'!E$10/'Source Data'!E$7 -> 0.12524775 | F8: ='Source Data'!F$10/'Source Data'!F$7 -> 0.11780342 | G8: 0.11 | H8: 0.106 | I8: 0.102 | J8: 0.098 | K8: 0.095 | M8: R&D is semi-fixed: it rose in dollars while revenue fell. Declining % implies ~3% p.a. dollar growth.
A9: SG&A % of revenue | B9: ='Source Data'!B$11/'Source Data'!B$7 -> 0.090819887 | C9: ='Source Data'!C$11/'Source Data'!C$7 -> 0.085080887 | D9: ='Source Data'!D$11/'Source Data'!D$7 -> 0.10417261 | E9: ='Source Data'!E$11/'Source Data'!E$7 -> 0.11469855 | F9: ='Source Data'!F$11/'Source Data'!F$7 -> 0.10519172 | G9: 0.1 | H9: 0.096 | I9: 0.092 | J9: 0.09 | K9: 0.088 | M9: Same logic as R&D. Implies ~3-4% p.a. dollar growth.
A10: Other operating expense/(income) % of revenue | B10: =('Source Data'!B$9-'Source Data'!B$10-'Source Data'!B$11-'Source Data'!B$12)/'Source Data'!B$7 -> 0.010684693 | C10: =('Source Data'!C$9-'Source Data'!C$10-'Source Data'!C$11-'Source Data'!C$12)/'Source Data'!C$7 -> 0.012832035 | D10: =('Source Data'!D$9-'Source Data'!D$10-'Source Data'!D$11-'Source Data'!D$12)/'Source Data'!D$7 -> 0 | E10: =('Source Data'!E$9-'Source Data'!E$10-'Source Data'!E$11-'Source Data'!E$12)/'Source Data'!E$7 -> -0.0079278818 | F10: =('Source Data'!F$9-'Source Data'!F$10-'Source Data'!F$11-'Source Data'!F$12)/'Source Data'!F$7 -> 0.0066168985 | G10: 0 | H10: 0 | I10: 0 | J10: 0 | K10: 0 | M10: Restructuring / acquisition charges. Historically -0.8% to +1.3% of revenue and it swung to a NET CREDIT in FY2024. Not forecastable; set to zero.
A11: Effective tax rate | B11: ='Source Data'!B$15/'Source Data'!B$14 -> 0.12893822 | C11: ='Source Data'!C$15/'Source Data'!C$14 -> 0.12789075 | D11: ='Source Data'!D$15/'Source Data'!D$14 -> 0.12240496 | E11: ='Source Data'!E$15/'Source Data'!E$14 -> 0.11993398 | F11: ='Source Data'!F$15/'Source Data'!F$14 -> 0.12416813 | G11: 0.14 | H11: 0.14 | I11: 0.14 | J11: 0.14 | K11: 0.14 | M11: FLAG: actual ETR is only 12.0-12.9% (FDII, R&D credits). Forecast at 14.0% to allow for the FDII deduction step-down and Pillar Two. Holding 12.4% adds roughly $6/share.
A12: BELOW THE LINE
A13: Interest rate on average total debt | B13: ='Source Data'!B$13/AVERAGE('Source Data'!B$32+'Source Data'!B$31,'Source Data'!$B$43+'Source Data'!$B$44) -> 0.025311232 | C13: ='Source Data'!C$13/AVERAGE('Source Data'!C$32+'Source Data'!C$31,'Source Data'!B$32+'Source Data'!B$31) -> 0.025977179 | D13: ='Source Data'!D$13/AVERAGE('Source Data'!D$32+'Source Data'!D$31,'Source Data'!C$32+'Source Data'!C$31) -> 0.035374286 | E13: ='Source Data'!E$13/AVERAGE('Source Data'!E$32+'Source Data'!E$31,'Source Data'!D$32+'Source Data'!D$31) -> 0.040936379 | F13: ='Source Data'!F$13/AVERAGE('Source Data'!F$32+'Source Data'!F$31,'Source Data'!E$32+'Source Data'!E$31) -> 0.039285198 | G13: 0.043 | H13: 0.043 | I13: 0.043 | J13: 0.043 | K13: 0.043 | M13: Effective rate rose 2.5% -> 3.9% as low-coupon 2021-22 issuance was topped up at higher rates. 4.3% assumes continued refinancing upward.
A14: Yield on average cash and short-term investments | B14: n/a | C14: ='Income Statement'!C$19/('Balance Sheet'!B$6+'Balance Sheet'!B$7) -> 0.010522136 | D14: ='Income Statement'!D$19/('Balance Sheet'!C$6+'Balance Sheet'!C$7) -> 0.04696339 | E14: ='Income Statement'!E$19/('Balance Sheet'!D$6+'Balance Sheet'!D$7) -> 0.053127678 | F14: ='Income Statement'!F$19/('Balance Sheet'!E$6+'Balance Sheet'!E$7) -> 0.0261959 | G14: 0.03 | H14: 0.03 | I14: 0.03 | J14: 0.03 | K14: 0.03 | M14: Drives the 'Other income/(expense), net' line, which historically is mostly interest income on the investment portfolio (residual was $143m-$496m).
A15: CAPITAL INTENSITY AND WORKING CAPITAL
A16: Capex % of revenue | B16: ='Source Data'!B$20/'Source Data'!B$7 -> 0.13421282 | C16: ='Source Data'!C$20/'Source Data'!C$7 -> 0.13965448 | D16: ='Source Data'!D$20/'Source Data'!D$7 -> 0.28945716 | E16: ='Source Data'!E$20/'Source Data'!E$7 -> 0.30816444 | F16: ='Source Data'!F$20/'Source Data'!F$7 -> 0.25732383 | G16: 0.22 | H16: 0.18 | I16: 0.15 | J16: 0.13 | K16: 0.12 | M16: THE key swing factor. Capex ran 4-7% of revenue pre-2021 and 26-31% in FY2023-25 for the Sherman/Lehi build-out. Assumes a taper, not a return to 5%.
A17: D&A as % of opening net PP&E | B17: ='Source Data'!B$19/'Source Data'!$B$42 -> 0.23095748 | C17: ='Source Data'!C$19/'Source Data'!B$27 -> 0.17992608 | D17: ='Source Data'!D$19/'Source Data'!C$27 -> 0.17088424 | E17: ='Source Data'!E$19/'Source Data'!D$27 -> 0.15081508 | F17: ='Source Data'!F$19/'Source Data'!E$27 -> 0.16903146 | G17: 0.16 | H17: 0.16 | I17: 0.16 | J17: 0.16 | K17: 0.16 | M17: Recent actuals 15-18%. D&A nearly trebled ($755m -> $1,918m) and keeps climbing as the new fabs are placed in service — a permanent drag on gross margin.
A18: Days sales outstanding | B18: ='Source Data'!B$24/'Source Data'!B$7*365 -> 33.845672 | C18: ='Source Data'!C$24/'Source Data'!C$7*365 -> 34.5354 | D18: ='Source Data'!D$24/'Source Data'!D$7*365 -> 37.231292 | E18: ='Source Data'!E$24/'Source Data'!E$7*365 -> 40.114762 | F18: ='Source Data'!F$24/'Source Data'!F$7*365 -> 40.521151 | G18: 40 | H18: 40 | I18: 40 | J18: 40 | K18: 40 | M18: FY2025 actual 40.5 days.
A19: Days inventory outstanding | B19: ='Source Data'!B$25/'Source Data'!B$8*365 -> 116.81468 | C19: ='Source Data'!C$25/'Source Data'!C$8*365 -> 160.82867 | D19: ='Source Data'!D$25/'Source Data'!D$8*365 -> 224.55923 | E19: ='Source Data'!E$25/'Source Data'!E$8*365 -> 252.38353 | F19: ='Source Data'!F$25/'Source Data'!F$8*365 -> 230.74878 | G19: 220 | H19: 210 | I19: 200 | J19: 195 | K19: 190 | M19: FLAG: inventory built from 117 to 253 days over four years, then eased to 231. Assumes a gradual unwind to 190 days. Every 10 days of DIO is roughly $200m of cash.
A20: Days payable outstanding | B20: ='Source Data'!B$29/'Source Data'!B$8*365 -> 34.922084 | C20: ='Source Data'!C$29/'Source Data'!C$8*365 -> 49.6428 | D20: ='Source Data'!D$29/'Source Data'!D$8*365 -> 45.035385 | E20: ='Source Data'!E$29/'Source Data'!E$8*365 -> 45.715595 | F20: ='Source Data'!F$29/'Source Data'!F$8*365 -> 36.312673 | G20: 38 | H20: 38 | I20: 38 | J20: 38 | K20: 38 | M20: FY2025 actual 36.3 days.
A21: FINANCING AND CAPITAL RETURNS
A22: Other non-cash and deferred items, % of revenue | B22: ='Cash Flow'!B$8/'Income Statement'!B$6 -> 0.017335369 | C22: ='Cash Flow'!C$8/'Income Statement'!C$6 -> -0.0096365089 | D22: ='Cash Flow'!D$8/'Income Statement'!D$6 -> -0.0046806325 | E22: ='Cash Flow'!E$8/'Income Statement'!E$6 -> 0.028962343 | F22: ='Cash Flow'!F$8/'Income Statement'!F$6 -> 0.04631829 | G22: 0.02 | H22: 0.02 | I22: 0.02 | J22: 0.02 | K22: 0.02 | M22: Stock compensation, deferred tax and other non-cash. Historically the residual between reported CFO and (net income + D&A - working capital): +1.7%, -1.0%, -0.5%, +2.9%, +4.6%. 2.0% is the mid.
A23: Long-term debt, non-current (held flat) | B23: ='Source Data'!B$32 -> 7241 | C23: ='Source Data'!C$32 -> 8235 | D23: ='Source Data'!D$32 -> 10624 | E23: ='Source Data'!E$32 -> 12846 | F23: ='Source Data'!F$32 -> 13548 | G23: 13548 | H23: 13548 | I23: 13548 | J23: 13548 | K23: 13548 | M23: Total debt more than doubled ($6.8bn -> $14.0bn) to fund capex and the dividend. Held flat here; cash is the balancing item.
A24: Long-term debt, current portion (held flat) | B24: ='Source Data'!B$31 -> 500 | C24: ='Source Data'!C$31 -> 500 | D24: ='Source Data'!D$31 -> 599 | E24: ='Source Data'!E$31 -> 750 | F24: ='Source Data'!F$31 -> 500 | G24: 500 | H24: 500 | I24: 500 | J24: 500 | K24: 500
A25: Shareholder distributions (dividends + buybacks) | B25: ='Income Statement'!B$23+'Cash Flow'!B$8-('Balance Sheet'!B$22-'Source Data'!$B$45) -> 3941 | C25: ='Income Statement'!C$23+'Cash Flow'!C$8-('Balance Sheet'!C$22-'Balance Sheet'!B$22) -> 7312 | D25: ='Income Statement'!D$23+'Cash Flow'!D$8-('Balance Sheet'!D$22-'Balance Sheet'!C$22) -> 4108 | E25: ='Income Statement'!E$23+'Cash Flow'!E$8-('Balance Sheet'!E$22-'Balance Sheet'!D$22) -> 5246 | F25: ='Income Statement'!F$23+'Cash Flow'!F$8-('Balance Sheet'!F$22-'Balance Sheet'!E$22) -> 6450 | G25: 5900 | H25: =G25*(1+$H$26) -> 6136 | I25: =H25*(1+I$26) -> 6381.44 | J25: =I25*(1+J$26) -> 6636.6976 | K25: =J25*(1+K$26) -> 6902.1655 | M25: FLAG: dividends and buybacks are NOT in the source extract. The historical figures shown are DERIVED from the equity roll-forward (net income + non-cash equity credits - change in equity) and land at $3.9bn-$7.3bn. FY2026E is a hardcoded input; later years grow at the rate below.
A26: growth in distributions | B26: n/a | C26: n/a | D26: n/a | E26: n/a | F26: n/a | G26: n/a | H26: 0.04 | I26: 0.04 | J26: 0.04 | K26: 0.04 | M26: FY2026E is set in dollars above; FY2027E onward grow at this rate.
A27: Diluted share count change | B27: n/a | C27: ='Source Data'!C$17/'Source Data'!B$17-1 -> -0.010683761 | D27: ='Source Data'!D$17/'Source Data'!C$17-1 -> -0.010799136 | E27: ='Source Data'!E$17/'Source Data'!D$17-1 -> 0.0032751092 | F27: ='Source Data'!F$17/'Source Data'!E$17-1 -> -0.0065288357 | G27: -0.005 | H27: -0.005 | I27: -0.005 | J27: -0.005 | K27: -0.005 | M27: Buybacks were largely suspended to fund the fab programme: the count fell only 0.6% p.a. over five years vs 2-3% p.a. before that.
A28: BALANCE SHEET ITEMS HELD FLAT (not separately tagged in the extract)
A29: Short-term investments and other current assets (held flat) | B29: ='Source Data'!B$26-'Source Data'!B$23-'Source Data'!B$24-'Source Data'!B$25 -> 5443 | C29: ='Source Data'!C$26-'Source Data'!C$23-'Source Data'!C$24-'Source Data'!C$25 -> 6319 | D29: ='Source Data'!D$26-'Source Data'!D$23-'Source Data'!D$24-'Source Data'!D$25 -> 6372 | E29: ='Source Data'!E$26-'Source Data'!E$23-'Source Data'!E$24-'Source Data'!E$25 -> 5580 | F29: ='Source Data'!F$26-'Source Data'!F$23-'Source Data'!F$24-'Source Data'!F$25 -> 3758 | G29: 3758 | H29: 3758 | I29: 3758 | J29: 3758 | K29: 3758 | M29: Not separately tagged in the extract; derived as total current assets less cash, receivables and inventory. Held flat, so modelled cash absorbs the full funding swing (conservative — in practice this portfolio would be drawn first).
A30: Goodwill, intangibles and other long-term assets (held flat) | B30: ='Source Data'!B$28-'Source Data'!B$26-'Source Data'!B$27 -> 5850 | C30: ='Source Data'!C$28-'Source Data'!C$26-'Source Data'!C$27 -> 6310 | D30: ='Source Data'!D$28-'Source Data'!D$26-'Source Data'!D$27 -> 7227 | E30: ='Source Data'!E$28-'Source Data'!E$26-'Source Data'!E$27 -> 9136 | F30: ='Source Data'!F$28-'Source Data'!F$26-'Source Data'!F$27 -> 8515 | G30: 8515 | H30: 8515 | I30: 8515 | J30: 8515 | K30: 8515
A31: Other current liabilities (held flat) | B31: ='Source Data'!B$30-'Source Data'!B$29-'Source Data'!B$31 -> 1498 | C31: ='Source Data'!C$30-'Source Data'!C$29-'Source Data'!C$31 -> 1634 | D31: ='Source Data'!D$30-'Source Data'!D$29-'Source Data'!D$31 -> 1919 | E31: ='Source Data'!E$30-'Source Data'!E$29-'Source Data'!E$31 -> 2073 | F31: ='Source Data'!F$30-'Source Data'!F$29-'Source Data'!F$31 -> 1903 | G31: 1903 | H31: 1903 | I31: 1903 | J31: 1903 | K31: 1903
A32: Other long-term liabilities (held flat) | B32: ='Source Data'!B$33-'Source Data'!B$30-'Source Data'!B$32 -> 1533 | C32: ='Source Data'!C$33-'Source Data'!C$30-'Source Data'!C$32 -> 1410 | D32: ='Source Data'!D$33-'Source Data'!D$30-'Source Data'!D$32 -> 1507 | E32: ='Source Data'!E$33-'Source Data'!E$30-'Source Data'!E$32 -> 2117 | F32: ='Source Data'!F$33-'Source Data'!F$30-'Source Data'!F$32 -> 1605 | G32: 1605 | H32: 1605 | I32: 1605 | J32: 1605 | K32: 1605
A34: MODEL CONTROLS
A35: Minimum operating cash balance (checked on the Checks tab) | B35: 1000 | M35: Used only to raise a flag, not to force a revolver draw.

Sheet Income Statement
A1: Consolidated Income Statement
A2: Green = link to Source Data (as reported). Black = formula. All forecast lines are driven from the Assumptions tab.
A4: ($ in millions, except per-share) | B4: FY2021A | C4: FY2022A | D4: FY2023A | E4: FY2024A | F4: FY2025A | G4: FY2026E | H4: FY2027E | I4: FY2028E | J4: FY2029E | K4: FY2030E | M4: Notes / source
A5: REVENUE
A6: Revenue | B6: ='Source Data'!B$7 -> 18344 | C6: ='Source Data'!C$7 -> 20028 | D6: ='Source Data'!D$7 -> 17519 | E6: ='Source Data'!E$7 -> 15641 | F6: ='Source Data'!F$7 -> 17682 | G6: =F6*(1+Assumptions!G$6) -> 19450.2 | H6: =G6*(1+Assumptions!H$6) -> 21006.216 | I6: =H6*(1+Assumptions!I$6) -> 22476.651 | J6: =I6*(1+Assumptions!J$6) -> 23825.25 | K6: =J6*(1+Assumptions!K$6) -> 25016.513
A7: growth % | B7: n/a | C7: =C6/B6-1 -> 0.091801134 | D7: =D6/C6-1 -> -0.12527462 | E7: =E6/D6-1 -> -0.1071979 | F7: =F6/E6-1 -> 0.13049038 | G7: =G6/F6-1 -> 0.1 | H7: =H6/G6-1 -> 0.08 | I7: =I6/H6-1 -> 0.07 | J7: =J6/I6-1 -> 0.06 | K7: =K6/J6-1 -> 0.05
A8: Cost of revenue | B8: ='Source Data'!B$8 -> 5968 | C8: ='Source Data'!C$8 -> 6257 | D8: ='Source Data'!D$8 -> 6500 | E8: ='Source Data'!E$8 -> 6547 | F8: ='Source Data'!F$8 -> 7599 | G8: =G6*(1-Assumptions!G$7) -> 8169.084 | H8: =H6*(1-Assumptions!H$7) -> 8402.4864 | I8: =I6*(1-Assumptions!I$7) -> 8765.8939 | J8: =J6*(1-Assumptions!J$7) -> 9172.7213 | K8: =K6*(1-Assumptions!K$7) -> 9506.2748
A9: Gross profit | B9: =B6-B8 -> 12376 | C9: =C6-C8 -> 13771 | D9: =D6-D8 -> 11019 | E9: =E6-E8 -> 9094 | F9: =F6-F8 -> 10083 | G9: =G6-G8 -> 11281.116 | H9: =H6-H8 -> 12603.73 | I9: =I6-I8 -> 13710.757 | ... K9: =K6-K8 -> 15510.238
A10: gross margin % | B10: =B9/B6 -> 0.67466201 | C10: =C9/C6 -> 0.68758738 | D10: =D9/D6 -> 0.62897426 | E10: =E9/E6 -> 0.58142063 | F10: =F9/F6 -> 0.57024092 | G10: =G9/G6 -> 0.58 | H10: =H9/H6 -> 0.6 | I10: =I9/I6 -> 0.61 | ... K10: =K9/K6 -> 0.62
A11: OPERATING EXPENSES
A12: Research and development | B12: ='Source Data'!B$10 -> 1554 | C12: ='Source Data'!C$10 -> 1670 | D12: ='Source Data'!D$10 -> 1863 | E12: ='Source Data'!E$10 -> 1959 | F12: ='Source Data'!F$10 -> 2083 | G12: =G6*Assumptions!G$8 -> 2139.522 | H12: =H6*Assumptions!H$8 -> 2226.6589 | I12: =I6*Assumptions!I$8 -> 2292.6184 | J12: =J6*Assumptions!J$8 -> 2334.8745 | K12: =K6*Assumptions!K$8 -> 2376.5687
A13: Selling, general and administrative | B13: ='Source Data'!B$11 -> 1666 | C13: ='Source Data'!C$11 -> 1704 | D13: ='Source Data'!D$11 -> 1825 | E13: ='Source Data'!E$11 -> 1794 | F13: ='Source Data'!F$11 -> 1860 | G13: =G6*Assumptions!G$9 -> 1945.02 | H13: =H6*Assumptions!H$9 -> 2016.5967 | I13: =I6*Assumptions!I$9 -> 2067.8519 | J13: =J6*Assumptions!J$9 -> 2144.2725 | K13: =K6*Assumptions!K$9 -> 2201.4531
A14: Other operating expense / (income) | B14: =B9-B12-B13-'Source Data'!B$12 -> 196 | C14: =C9-C12-C13-'Source Data'!C$12 -> 257 | D14: =D9-D12-D13-'Source Data'!D$12 -> 0 | E14: =E9-E12-E13-'Source Data'!E$12 -> -124 | F14: =F9-F12-F13-'Source Data'!F$12 -> 117 | G14: =G6*Assumptions!G$10 -> 0 | H14: =H6*Assumptions!H$10 -> 0 | I14: =I6*Assumptions!I$10 -> 0 | J14: =J6*Assumptions!J$10 -> 0 | K14: =K6*Assumptions!K$10 -> 0 | M14: Historical column is the residual that reconciles gross profit less R&D and SG&A to reported operating income (restructuring and acquisition charges). Reconciled on the Checks tab.
A15: Operating income (EBIT) | B15: =B9-B12-B13-B14 -> 8960 | C15: =C9-C12-C13-C14 -> 10140 | D15: =D9-D12-D13-D14 -> 7331 | E15: =E9-E12-E13-E14 -> 5465 | F15: =F9-F12-F13-F14 -> 6023 | G15: =G9-G12-G13-G14 -> 7196.574 | H15: =H9-H12-H13-H14 -> 8360.474 | I15: =I9-I12-I13-I14 -> 9350.2869 | ... K15: =K9-K12-K13-K14 -> 10932.216
A16: operating margin % | B16: =B15/B6 -> 0.48844309 | C16: =C15/C6 -> 0.50629119 | D16: =D15/D6 -> 0.41845996 | E16: =E15/E6 -> 0.34940221 | F16: =F15/F6 -> 0.34062889 | G16: =G15/G6 -> 0.37 | H16: =H15/H6 -> 0.398 | I16: =I15/I6 -> 0.416 | ... K16: =K15/K6 -> 0.437
A17: NON-OPERATING
A18: Interest and debt expense | B18: ='Source Data'!B$13 -> 184 | C18: ='Source Data'!C$13 -> 214 | D18: ='Source Data'!D$13 -> 353 | E18: ='Source Data'!E$13 -> 508 | F18: ='Source Data'!F$13 -> 543 | G18: =AVERAGE(Assumptions!G$23+Assumptions!G$24,'Source Data'!F$32+'Source Data'!F$31)*Assumptions!G$13 -> 604.064 | H18: =AVERAGE(Assumptions!H$23+Assumptions!H$24,Assumptions!G$23+Assumptions!G$24)*Assumptions!H$13 -> 604.064 | I18: =AVERAGE(Assumptions!I$23+Assumptions!I$24,Assumptions!H$23+Assumptions!H$24)*Assumptions!I$13 -> 604.064 | J18: =AVERAGE(Assumptions!J$23+Assumptions!J$24,Assumptions!I$23+Assumptions!I$24)*Assumptions!J$13 -> 604.064 | K18: =AVERAGE(Assumptions!K$23+Assumptions!K$24,Assumptions!J$23+Assumptions!J$24)*Assumptions!K$13 -> 604.064
A19: Other income / (expense), net | B19: ='Source Data'!B$14-B15+B18 -> 143 | C19: ='Source Data'!C$14-C15+C18 -> 106 | D19: ='Source Data'!D$14-D15+D18 -> 440 | E19: ='Source Data'!E$14-E15+E18 -> 496 | F19: ='Source Data'!F$14-F15+F18 -> 230 | G19: =('Balance Sheet'!F$6+'Balance Sheet'!F$7)*Assumptions!G$14 -> 209.49 | H19: =('Balance Sheet'!G$6+'Balance Sheet'!G$7)*Assumptions!H$14 -> 144.59999 | I19: =('Balance Sheet'!H$6+'Balance Sheet'!H$7)*Assumptions!I$14 -> 132.0489 | J19: =('Balance Sheet'!I$6+'Balance Sheet'!I$7)*Assumptions!J$14 -> 156.36806 | K19: =('Balance Sheet'!J$6+'Balance Sheet'!J$7)*Assumptions!K$14 -> 204.45685 | M19: Historical column is the residual reconciling EBIT less interest expense to reported pre-tax income — predominantly interest income on the cash and investment portfolio. Forecast is calculated on the OPENING cash and investment balance rather than the average, which avoids a circular reference back into the cash plug.
A20: Pre-tax income | B20: =B15-B18+B19 -> 8919 | C20: =C15-C18+C19 -> 10032 | D20: =D15-D18+D19 -> 7418 | E20: =E15-E18+E19 -> 5453 | F20: =F15-F18+F19 -> 5710 | G20: =G15-G18+G19 -> 6802 | H20: =H15-H18+H19 -> 7901.01 | I20: =I15-I18+I19 -> 8878.2718 | ... K20: =K15-K18+K19 -> 10532.609
A21: Income tax expense | B21: ='Source Data'!B$15 -> 1150 | C21: ='Source Data'!C$15 -> 1283 | D21: ='Source Data'!D$15 -> 908 | E21: ='Source Data'!E$15 -> 654 | F21: ='Source Data'!F$15 -> 709 | G21: =G20*Assumptions!G$11 -> 952.28 | H21: =H20*Assumptions!H$11 -> 1106.1414 | I21: =I20*Assumptions!I$11 -> 1242.958 | J21: =J20*Assumptions!J$11 -> 1361.596 | K21: =K20*Assumptions!K$11 -> 1474.5652
A22: effective tax rate | B22: =B21/B20 -> 0.12893822 | C22: =C21/C20 -> 0.12789075 | D22: =D21/D20 -> 0.12240496 | E22: =E21/E20 -> 0.11993398 | F22: =F21/F20 -> 0.12416813 | G22: =G21/G20 -> 0.14 | H22: =H21/H20 -> 0.14 | I22: =I21/I20 -> 0.14 | ... K22: =K21/K20 -> 0.14
A23: Net income | B23: =B20-B21 -> 7769 | C23: =C20-C21 -> 8749 | D23: =D20-D21 -> 6510 | E23: =E20-E21 -> 4799 | F23: =F20-F21 -> 5001 | G23: =G20-G21 -> 5849.72 | H23: =H20-H21 -> 6794.8686 | I23: =I20-I21 -> 7635.3137 | ... K23: =K20-K21 -> 9058.0436
A24: net margin % | B24: =B23/B6 -> 0.42351723 | C24: =C23/C6 -> 0.43683843 | D24: =D23/D6 -> 0.37159655 | E24: =E23/E6 -> 0.30682181 | F24: =F23/F6 -> 0.28283 | G24: =G23/G6 -> 0.30075372 | H24: =H23/H6 -> 0.32346942 | I24: =I23/I6 -> 0.33969979 | ... K24: =K23/K6 -> 0.36208259
A25: PER SHARE
A26: Diluted weighted-average shares (mm) | B26: ='Source Data'!B$17 -> 936 | C26: ='Source Data'!C$17 -> 926 | D26: ='Source Data'!D$17 -> 916 | E26: ='Source Data'!E$17 -> 919 | F26: ='Source Data'!F$17 -> 913 | G26: =F26*(1+Assumptions!G$27) -> 908.435 | H26: =G26*(1+Assumptions!H$27) -> 903.89283 | I26: =H26*(1+Assumptions!I$27) -> 899.37336 | J26: =I26*(1+Assumptions!J$27) -> 894.87649 | K26: =J26*(1+Assumptions!K$27) -> 890.40211
A27: Diluted earnings per share | B27: =B23/B26 -> 8.3002137 | C27: =C23/C26 -> 9.4481641 | D27: =D23/D26 -> 7.1069869 | E27: =E23/E26 -> 5.2219804 | F27: =F23/F26 -> 5.4775465 | G27: =G23/G26 -> 6.439338 | H27: =H23/H26 -> 7.5173388 | I27: =I23/I26 -> 8.4895929 | ... K27: =K23/K26 -> 10.172981
A28: MEMO
A29: Memo: depreciation and amortisation | B29: ='Cash Flow'!B$7 -> 755 | C29: ='Cash Flow'!C$7 -> 925 | D29: ='Cash Flow'!D$7 -> 1175 | E29: ='Cash Flow'!E$7 -> 1508 | F29: ='Cash Flow'!F$7 -> 1918 | G29: ='Cash Flow'!G$7 -> 1971.2 | H29: ='Cash Flow'!H$7 -> 2340.455 | I29: ='Cash Flow'!I$7 -> 2570.9613 | ... K29: ='Cash Flow'!K$7 -> 2762.7648
A30: Memo: EBITDA | B30: =B15+B29 -> 9715 | C30: =C15+C29 -> 11065 | D30: =D15+D29 -> 8506 | E30: =E15+E29 -> 6973 | F30: =F15+F29 -> 7941 | G30: =G15+G29 -> 9167.774 | H30: =H15+H29 -> 10700.929 | I30: =I15+I29 -> 11921.248 | ... K30: =K15+K29 -> 13694.981
A31: EBITDA margin % | B31: =B30/B6 -> 0.52960096 | C31: =C30/C6 -> 0.55247653 | D31: =D30/D6 -> 0.48553 | E31: =E30/E6 -> 0.44581548 | F31: =F30/F6 -> 0.44910078 | G31: =G30/G6 -> 0.471346 | H31: =H30/H6 -> 0.50941726 | I31: =I30/I6 -> 0.53038364 | ... K31: =K30/K6 -> 0.54743765

Sheet Balance Sheet
A1: Consolidated Balance Sheet
A2: Historical columns are as reported, with four lines derived as residuals because the extract does not tag them separately (marked in the notes). Forecast cash is the balancing item — there is no revolver.
A4: ($ in millions, except per-share) | B4: FY2021A | C4: FY2022A | D4: FY2023A | E4: FY2024A | F4: FY2025A | G4: FY2026E | H4: FY2027E | I4: FY2028E | J4: FY2029E | K4: FY2030E | M4: Notes / source
A5: ASSETS
A6: Cash and cash equivalents | B6: ='Source Data'!B$23 -> 4631 | C6: ='Source Data'!C$23 -> 3050 | D6: ='Source Data'!D$23 -> 2964 | E6: ='Source Data'!E$23 -> 3200 | F6: ='Source Data'!F$23 -> 3225 | G6: ='Cash Flow'!G$24 -> 1061.9998 | H6: ='Cash Flow'!H$24 -> 643.63014 | I6: ='Cash Flow'!I$24 -> 1454.2688 | J6: ='Cash Flow'!J$24 -> 3057.2282 | K6: ='Cash Flow'!K$24 -> 5330.4197
A7: Short-term investments and other current assets | B7: ='Source Data'!B$26-'Source Data'!B$23-'Source Data'!B$24-'Source Data'!B$25 -> 5443 | C7: ='Source Data'!C$26-'Source Data'!C$23-'Source Data'!C$24-'Source Data'!C$25 -> 6319 | D7: ='Source Data'!D$26-'Source Data'!D$23-'Source Data'!D$24-'Source Data'!D$25 -> 6372 | E7: ='Source Data'!E$26-'Source Data'!E$23-'Source Data'!E$24-'Source Data'!E$25 -> 5580 | F7: ='Source Data'!F$26-'Source Data'!F$23-'Source Data'!F$24-'Source Data'!F$25 -> 3758 | G7: =Assumptions!G$29 -> 3758 | H7: =Assumptions!H$29 -> 3758 | I7: =Assumptions!I$29 -> 3758 | J7: =Assumptions!J$29 -> 3758 | K7: =Assumptions!K$29 -> 3758 | M7: DERIVED: total current assets less cash, receivables and inventory. Not separately tagged in the extract.
A8: Accounts receivable, net | B8: ='Source Data'!B$24 -> 1701 | C8: ='Source Data'!C$24 -> 1895 | D8: ='Source Data'!D$24 -> 1787 | E8: ='Source Data'!E$24 -> 1719 | F8: ='Source Data'!F$24 -> 1963 | G8: =Assumptions!G$18/365*'Income Statement'!G$6 -> 2131.5288 | H8: =Assumptions!H$18/365*'Income Statement'!H$6 -> 2302.0511 | I8: =Assumptions!I$18/365*'Income Statement'!I$6 -> 2463.1946 | J8: =Assumptions!J$18/365*'Income Statement'!J$6 -> 2610.9863 | K8: =Assumptions!K$18/365*'Income Statement'!K$6 -> 2741.5356
A9: Inventory, net | B9: ='Source Data'!B$25 -> 1910 | C9: ='Source Data'!C$25 -> 2757 | D9: ='Source Data'!D$25 -> 3999 | E9: ='Source Data'!E$25 -> 4527 | F9: ='Source Data'!F$25 -> 4804 | G9: =Assumptions!G$19/365*'Income Statement'!G$8 -> 4923.8315 | H9: =Assumptions!H$19/365*'Income Statement'!H$8 -> 4834.3072 | I9: =Assumptions!I$19/365*'Income Statement'!I$8 -> 4803.2296 | J9: =Assumptions!J$19/365*'Income Statement'!J$8 -> 4900.495 | K9: =Assumptions!K$19/365*'Income Statement'!K$8 -> 4948.4718
A10: Total current assets | B10: =SUM(B6:B9) -> 13685 | C10: =SUM(C6:C9) -> 14021 | D10: =SUM(D6:D9) -> 15122 | E10: =SUM(E6:E9) -> 15026 | F10: =SUM(F6:F9) -> 13750 | G10: =SUM(G6:G9) -> 11875.36 | H10: =SUM(H6:H9) -> 11537.988 | I10: =SUM(I6:I9) -> 12478.693 | ... K10: =SUM(K6:K9) -> 16778.427
A11: Property, plant and equipment, net | B11: ='Source Data'!B$27 -> 5141 | C11: ='Source Data'!C$27 -> 6876 | D11: ='Source Data'!D$27 -> 9999 | E11: ='Source Data'!E$27 -> 11347 | F11: ='Source Data'!F$27 -> 12320 | G11: ='Balance Sheet'!F$11-'Cash Flow'!G$14-'Cash Flow'!G$7 -> 14627.844 | H11: ='Balance Sheet'!G$11-'Cash Flow'!H$14-'Cash Flow'!H$7 -> 16068.508 | I11: ='Balance Sheet'!H$11-'Cash Flow'!I$14-'Cash Flow'!I$7 -> 16869.044 | J11: ='Balance Sheet'!I$11-'Cash Flow'!J$14-'Cash Flow'!J$7 -> 17267.28 | K11: ='Balance Sheet'!J$11-'Cash Flow'!K$14-'Cash Flow'!K$7 -> 17506.496
A12: Goodwill, intangibles and other long-term assets | B12: ='Source Data'!B$28-'Source Data'!B$26-'Source Data'!B$27 -> 5850 | C12: ='Source Data'!C$28-'Source Data'!C$26-'Source Data'!C$27 -> 6310 | D12: ='Source Data'!D$28-'Source Data'!D$26-'Source Data'!D$27 -> 7227 | E12: ='Source Data'!E$28-'Source Data'!E$26-'Source Data'!E$27 -> 9136 | F12: ='Source Data'!F$28-'Source Data'!F$26-'Source Data'!F$27 -> 8515 | G12: =Assumptions!G$30 -> 8515 | H12: =Assumptions!H$30 -> 8515 | I12: =Assumptions!I$30 -> 8515 | J12: =Assumptions!J$30 -> 8515 | K12: =Assumptions!K$30 -> 8515 | M12: DERIVED: total assets less current assets less net PP&E. Not separately tagged in the extract.
A13: TOTAL ASSETS | B13: =B10+B11+B12 -> 24676 | C13: =C10+C11+C12 -> 27207 | D13: =D10+D11+D12 -> 32348 | E13: =E10+E11+E12 -> 35509 | F13: =F10+F11+F12 -> 34585 | G13: =G10+G11+G12 -> 35018.204 | H13: =H10+H11+H12 -> 36121.496 | I13: =I10+I11+I12 -> 37862.737 | ... K13: =K10+K11+K12 -> 42799.924
A14: LIABILITIES AND EQUITY
A15: Accounts payable | B15: ='Source Data'!B$29 -> 571 | C15: ='Source Data'!C$29 -> 851 | D15: ='Source Data'!D$29 -> 802 | E15: ='Source Data'!E$29 -> 820 | F15: ='Source Data'!F$29 -> 756 | G15: =Assumptions!G$20/365*'Income Statement'!G$8 -> 850.47998 | H15: =Assumptions!H$20/365*'Income Statement'!H$8 -> 874.77941 | I15: =Assumptions!I$20/365*'Income Statement'!I$8 -> 912.61362 | J15: =Assumptions!J$20/365*'Income Statement'!J$8 -> 954.96825 | K15: =Assumptions!K$20/365*'Income Statement'!K$8 -> 989.69437
A16: Long-term debt, current portion | B16: ='Source Data'!B$31 -> 500 | C16: ='Source Data'!C$31 -> 500 | D16: ='Source Data'!D$31 -> 599 | E16: ='Source Data'!E$31 -> 750 | F16: ='Source Data'!F$31 -> 500 | G16: =Assumptions!G$24 -> 500 | H16: =Assumptions!H$24 -> 500 | I16: =Assumptions!I$24 -> 500 | J16: =Assumptions!J$24 -> 500 | K16: =Assumptions!K$24 -> 500
A17: Other current liabilities | B17: ='Source Data'!B$30-'Source Data'!B$29-'Source Data'!B$31 -> 1498 | C17: ='Source Data'!C$30-'Source Data'!C$29-'Source Data'!C$31 -> 1634 | D17: ='Source Data'!D$30-'Source Data'!D$29-'Source Data'!D$31 -> 1919 | E17: ='Source Data'!E$30-'Source Data'!E$29-'Source Data'!E$31 -> 2073 | F17: ='Source Data'!F$30-'Source Data'!F$29-'Source Data'!F$31 -> 1903 | G17: =Assumptions!G$31 -> 1903 | H17: =Assumptions!H$31 -> 1903 | I17: =Assumptions!I$31 -> 1903 | J17: =Assumptions!J$31 -> 1903 | K17: =Assumptions!K$31 -> 1903 | M17: DERIVED: total current liabilities less payables less current portion of debt (accrued compensation, taxes payable, etc.).
A18: Total current liabilities | B18: =SUM(B15:B17) -> 2569 | C18: =SUM(C15:C17) -> 2985 | D18: =SUM(D15:D17) -> 3320 | E18: =SUM(E15:E17) -> 3643 | F18: =SUM(F15:F17) -> 3159 | G18: =SUM(G15:G17) -> 3253.48 | H18: =SUM(H15:H17) -> 3277.7794 | I18: =SUM(I15:I17) -> 3315.6136 | ... K18: =SUM(K15:K17) -> 3392.6944
A19: Long-term debt, non-current | B19: ='Source Data'!B$32 -> 7241 | C19: ='Source Data'!C$32 -> 8235 | D19: ='Source Data'!D$32 -> 10624 | E19: ='Source Data'!E$32 -> 12846 | F19: ='Source Data'!F$32 -> 13548 | G19: =Assumptions!G$23 -> 13548 | H19: =Assumptions!H$23 -> 13548 | I19: =Assumptions!I$23 -> 13548 | J19: =Assumptions!J$23 -> 13548 | K19: =Assumptions!K$23 -> 13548
A20: Other long-term liabilities | B20: ='Source Data'!B$33-'Source Data'!B$30-'Source Data'!B$32 -> 1533 | C20: ='Source Data'!C$33-'Source Data'!C$30-'Source Data'!C$32 -> 1410 | D20: ='Source Data'!D$33-'Source Data'!D$30-'Source Data'!D$32 -> 1507 | E20: ='Source Data'!E$33-'Source Data'!E$30-'Source Data'!E$32 -> 2117 | F20: ='Source Data'!F$33-'Source Data'!F$30-'Source Data'!F$32 -> 1605 | G20: =Assumptions!G$32 -> 1605 | H20: =Assumptions!H$32 -> 1605 | I20: =Assumptions!I$32 -> 1605 | J20: =Assumptions!J$32 -> 1605 | K20: =Assumptions!K$32 -> 1605 | M20: DERIVED: total liabilities less current liabilities less long-term debt (deferred tax, pension, leases).
A21: Total liabilities | B21: =B18+B19+B20 -> 11343 | C21: =C18+C19+C20 -> 12630 | D21: =D18+D19+D20 -> 15451 | E21: =E18+E19+E20 -> 18606 | F21: =F18+F19+F20 -> 18312 | G21: =G18+G19+G20 -> 18406.48 | H21: =H18+H19+H20 -> 18430.779 | I21: =I18+I19+I20 -> 18468.614 | ... K21: =K18+K19+K20 -> 18545.694
A22: Total stockholders equity | B22: ='Source Data'!B$34 -> 13333 | C22: ='Source Data'!C$34 -> 14577 | D22: ='Source Data'!D$34 -> 16897 | E22: ='Source Data'!E$34 -> 16903 | F22: ='Source Data'!F$34 -> 16273 | G22: ='Balance Sheet'!F$22+'Income Statement'!G$23+'Cash Flow'!G$8+'Cash Flow'!G$19 -> 16611.724 | H22: ='Balance Sheet'!G$22+'Income Statement'!H$23+'Cash Flow'!H$8+'Cash Flow'!H$19 -> 17690.717 | I22: ='Balance Sheet'!H$22+'Income Statement'!I$23+'Cash Flow'!I$8+'Cash Flow'!I$19 -> 19394.124 | J22: ='Balance Sheet'!I$22+'Income Statement'!J$23+'Cash Flow'!J$8+'Cash Flow'!J$19 -> 21598.021 | K22: ='Balance Sheet'!J$22+'Income Statement'!K$23+'Cash Flow'!K$8+'Cash Flow'!K$19 -> 24254.229 | M22: Forecast roll-forward: opening equity + net income + non-cash equity credits (stock compensation and other) - cash distributions.
A23: TOTAL LIABILITIES AND EQUITY | B23: =B21+B22 -> 24676 | C23: =C21+C22 -> 27207 | D23: =D21+D22 -> 32348 | E23: =E21+E22 -> 35509 | F23: =F21+F22 -> 34585 | G23: =G21+G22 -> 35018.204 | H23: =H21+H22 -> 36121.496 | I23: =I21+I22 -> 37862.737 | ... K23: =K21+K22 -> 42799.924
A24: BALANCE CHECK
A25: CHECK: total assets less total liabilities and equity | B25: =B13-B23 -> 0 | C25: =C13-C23 -> 0 | D25: =D13-D23 -> 0 | E25: =E13-E23 -> 0 | F25: =F13-F23 -> 0 | G25: =G13-G23 -> 0 | H25: =H13-H23 -> 0 | I25: =I13-I23 -> 0 | ... K25: =K13-K23 -> 0
A26: MEMO
A27: Memo: total debt | B27: =B16+B19 -> 7741 | C27: =C16+C19 -> 8735 | D27: =D16+D19 -> 11223 | E27: =E16+E19 -> 13596 | F27: =F16+F19 -> 14048 | G27: =G16+G19 -> 14048 | H27: =H16+H19 -> 14048 | I27: =I16+I19 -> 14048 | ... K27: =K16+K19 -> 14048
A28: Memo: net debt (total debt less cash) | B28: =B27-B6 -> 3110 | C28: =C27-C6 -> 5685 | D28: =D27-D6 -> 8259 | E28: =E27-E6 -> 10396 | F28: =F27-F6 -> 10823 | G28: =G27-G6 -> 12986 | H28: =H27-H6 -> 13404.37 | I28: =I27-I6 -> 12593.731 | ... K28: =K27-K6 -> 8717.5803
A29: Memo: operating working capital (AR + inventory - AP) | B29: =B8+B9-B15 -> 3040 | C29: =C8+C9-C15 -> 3801 | D29: =D8+D9-D15 -> 4984 | E29: =E8+E9-E15 -> 5426 | F29: =F8+F9-F15 -> 6011 | G29: =G8+G9-G15 -> 6204.8802 | H29: =H8+H9-H15 -> 6261.5789 | I29: =I8+I9-I15 -> 6353.8106 | ... K29: =K8+K9-K15 -> 6700.3131

Sheet Cash Flow
A1: Consolidated Cash Flow Statement
A2: Historical operating cash flow ties exactly to the reported figure by construction (the non-cash line is the residual). The extract contains no investing or financing detail beyond capex, so those historical lines are derived — see notes.
A4: ($ in millions, except per-share) | B4: FY2021A | C4: FY2022A | D4: FY2023A | E4: FY2024A | F4: FY2025A | G4: FY2026E | H4: FY2027E | I4: FY2028E | J4: FY2029E | K4: FY2030E | M4: Notes / source
A5: OPERATING ACTIVITIES
A6: Net income | B6: ='Income Statement'!B$23 -> 7769 | C6: ='Income Statement'!C$23 -> 8749 | D6: ='Income Statement'!D$23 -> 6510 | E6: ='Income Statement'!E$23 -> 4799 | F6: ='Income Statement'!F$23 -> 5001 | G6: ='Income Statement'!G$23 -> 5849.72 | H6: ='Income Statement'!H$23 -> 6794.8686 | I6: ='Income Statement'!I$23 -> 7635.3137 | ... K6: ='Income Statement'!K$23 -> 9058.0436
A7: Depreciation and amortisation | B7: ='Source Data'!B$19 -> 755 | C7: ='Source Data'!C$19 -> 925 | D7: ='Source Data'!D$19 -> 1175 | E7: ='Source Data'!E$19 -> 1508 | F7: ='Source Data'!F$19 -> 1918 | G7: ='Balance Sheet'!F$11*Assumptions!G$17 -> 1971.2 | H7: ='Balance Sheet'!G$11*Assumptions!H$17 -> 2340.455 | I7: ='Balance Sheet'!H$11*Assumptions!I$17 -> 2570.9613 | J7: ='Balance Sheet'!I$11*Assumptions!J$17 -> 2699.0471 | K7: ='Balance Sheet'!J$11*Assumptions!K$17 -> 2762.7648 | M7: Historical is the XBRL 'Depreciation' tag. Forecast is the assumed rate applied to opening net PP&E.
A8: Other non-cash and deferred items | B8: ='Source Data'!B$21-B6-B7-(B9+B10+B11) -> 318 | C8: ='Source Data'!C$21-C6-C7-(C9+C10+C11) -> -193 | D8: ='Source Data'!D$21-D6-D7-(D9+D10+D11) -> -82 | E8: ='Source Data'!E$21-E6-E7-(E9+E10+E11) -> 453 | F8: ='Source Data'!F$21-F6-F7-(F9+F10+F11) -> 819 | G8: ='Income Statement'!G$6*Assumptions!G$22 -> 389.004 | H8: ='Income Statement'!H$6*Assumptions!H$22 -> 420.12432 | I8: ='Income Statement'!I$6*Assumptions!I$22 -> 449.53302 | J8: ='Income Statement'!J$6*Assumptions!J$22 -> 476.505 | K8: ='Income Statement'!K$6*Assumptions!K$22 -> 500.33025 | M8: Stock compensation, deferred tax and other. Historical column is the residual that forces modelled operating cash flow onto the reported figure.
A9: (Increase) / decrease in accounts receivable | B9: =-('Balance Sheet'!B$8-'Source Data'!$B$39) -> -287 | C9: =-('Balance Sheet'!C$8-'Balance Sheet'!B$8) -> -194 | D9: =-('Balance Sheet'!D$8-'Balance Sheet'!C$8) -> 108 | E9: =-('Balance Sheet'!E$8-'Balance Sheet'!D$8) -> 68 | F9: =-('Balance Sheet'!F$8-'Balance Sheet'!E$8) -> -244 | G9: =-('Balance Sheet'!G$8-'Balance Sheet'!F$8) -> -168.52877 | H9: =-('Balance Sheet'!H$8-'Balance Sheet'!G$8) -> -170.5223 | I9: =-('Balance Sheet'!I$8-'Balance Sheet'!H$8) -> -161.14357 | J9: =-('Balance Sheet'!J$8-'Balance Sheet'!I$8) -> -147.79168 | K9: =-('Balance Sheet'!K$8-'Balance Sheet'!J$8) -> -130.54932
A10: (Increase) / decrease in inventory | B10: =-('Balance Sheet'!B$9-'Source Data'!$B$40) -> 45 | C10: =-('Balance Sheet'!C$9-'Balance Sheet'!B$9) -> -847 | D10: =-('Balance Sheet'!D$9-'Balance Sheet'!C$9) -> -1242 | E10: =-('Balance Sheet'!E$9-'Balance Sheet'!D$9) -> -528 | F10: =-('Balance Sheet'!F$9-'Balance Sheet'!E$9) -> -277 | G10: =-('Balance Sheet'!G$9-'Balance Sheet'!F$9) -> -119.83145 | H10: =-('Balance Sheet'!H$9-'Balance Sheet'!G$9) -> 89.524208 | I10: =-('Balance Sheet'!I$9-'Balance Sheet'!H$9) -> 31.077689 | J10: =-('Balance Sheet'!J$9-'Balance Sheet'!I$9) -> -97.265398 | K10: =-('Balance Sheet'!K$9-'Balance Sheet'!J$9) -> -47.976874
A11: Increase / (decrease) in accounts payable | B11: ='Balance Sheet'!B$15-'Source Data'!$B$41 -> 156 | C11: ='Balance Sheet'!C$15-'Balance Sheet'!B$15 -> 280 | D11: ='Balance Sheet'!D$15-'Balance Sheet'!C$15 -> -49 | E11: ='Balance Sheet'!E$15-'Balance Sheet'!D$15 -> 18 | F11: ='Balance Sheet'!F$15-'Balance Sheet'!E$15 -> -64 | G11: ='Balance Sheet'!G$15-'Balance Sheet'!F$15 -> 94.479978 | H11: ='Balance Sheet'!H$15-'Balance Sheet'!G$15 -> 24.299428 | I11: ='Balance Sheet'!I$15-'Balance Sheet'!H$15 -> 37.834209 | J11: ='Balance Sheet'!J$15-'Balance Sheet'!I$15 -> 42.354632 | K11: ='Balance Sheet'!K$15-'Balance Sheet'!J$15 -> 34.726118
A12: CASH FLOW FROM OPERATIONS | B12: =SUM(B6:B11) -> 8756 | C12: =SUM(C6:C11) -> 8720 | D12: =SUM(D6:D11) -> 6420 | E12: =SUM(E6:E11) -> 6318 | F12: =SUM(F6:F11) -> 7153 | G12: =SUM(G6:G11) -> 8016.0438 | H12: =SUM(H6:H11) -> 9498.7493 | I12: =SUM(I6:I11) -> 10563.576 | ... K12: =SUM(K6:K11) -> 12177.339
A13: INVESTING ACTIVITIES
A14: Capital expenditure | B14: =-'Source Data'!B$20 -> -2462 | C14: =-'Source Data'!C$20 -> -2797 | D14: =-'Source Data'!D$20 -> -5071 | E14: =-'Source Data'!E$20 -> -4820 | F14: =-'Source Data'!F$20 -> -4550 | G14: =-'Income Statement'!G$6*Assumptions!G$16 -> -4279.044 | H14: =-'Income Statement'!H$6*Assumptions!H$16 -> -3781.1189 | I14: =-'Income Statement'!I$6*Assumptions!I$16 -> -3371.4977 | J14: =-'Income Statement'!J$6*Assumptions!J$16 -> -3097.2825 | K14: =-'Income Statement'!K$6*Assumptions!K$16 -> -3001.9815
A15: Net (purchases) / maturities of investments and other investing | B15: =('Balance Sheet'!B$6-'Source Data'!$B$38)-B12-B14-B20 -> -1772 | C15: =('Balance Sheet'!C$6-'Balance Sheet'!B$6)-C12-C14-C20 -> -1186 | D15: =('Balance Sheet'!D$6-'Balance Sheet'!C$6)-D12-D14-D20 -> 185 | E15: =('Balance Sheet'!E$6-'Balance Sheet'!D$6)-E12-E14-E20 -> 1611 | F15: =('Balance Sheet'!F$6-'Balance Sheet'!E$6)-F12-F14-F20 -> 3420 | G15: 0 | H15: 0 | I15: 0 | J15: 0 | K15: 0 | M15: DERIVED PLUG for history: the extract has no investing detail beyond capex, so this line absorbs the movement in the short-term investment portfolio and everything else, forcing cash to tie to the reported balance sheet. Set to zero in the forecast.
A16: CASH FLOW FROM INVESTING | B16: =B14+B15 -> -4234 | C16: =C14+C15 -> -3983 | D16: =D14+D15 -> -4886 | E16: =E14+E15 -> -3209 | F16: =F14+F15 -> -1130 | G16: =G14+G15 -> -4279.044 | H16: =H14+H15 -> -3781.1189 | I16: =I14+I15 -> -3371.4977 | ... K16: =K14+K15 -> -3001.9815
A17: FINANCING ACTIVITIES
A18: Net increase / (decrease) in total debt | B18: ='Balance Sheet'!B$27-('Source Data'!$B$43+'Source Data'!$B$44) -> 943 | C18: ='Balance Sheet'!C$27-'Balance Sheet'!B$27 -> 994 | D18: ='Balance Sheet'!D$27-'Balance Sheet'!C$27 -> 2488 | E18: ='Balance Sheet'!E$27-'Balance Sheet'!D$27 -> 2373 | F18: ='Balance Sheet'!F$27-'Balance Sheet'!E$27 -> 452 | G18: ='Balance Sheet'!G$27-'Balance Sheet'!F$27 -> 0 | H18: ='Balance Sheet'!H$27-'Balance Sheet'!G$27 -> 0 | I18: ='Balance Sheet'!I$27-'Balance Sheet'!H$27 -> 0 | J18: ='Balance Sheet'!J$27-'Balance Sheet'!I$27 -> 0 | K18: ='Balance Sheet'!K$27-'Balance Sheet'!J$27 -> 0
A19: Shareholder distributions (dividends and buybacks) | B19: =-Assumptions!B$25 -> -3941 | C19: =-Assumptions!C$25 -> -7312 | D19: =-Assumptions!D$25 -> -4108 | E19: =-Assumptions!E$25 -> -5246 | F19: =-Assumptions!F$25 -> -6450 | G19: =-Assumptions!G$25 -> -5900 | H19: =-Assumptions!H$25 -> -6136 | I19: =-Assumptions!I$25 -> -6381.44 | ... K19: =-Assumptions!K$25 -> -6902.1655 | M19: FLAG: not in the source extract. History is derived from the equity roll-forward; forecast is an input on the Assumptions tab. Single largest modelled (rather than reported) cash item.
A20: CASH FLOW FROM FINANCING | B20: =B18+B19 -> -2998 | C20: =C18+C19 -> -6318 | D20: =D18+D19 -> -1620 | E20: =E18+E19 -> -2873 | F20: =F18+F19 -> -5998 | G20: =G18+G19 -> -5900 | H20: =H18+H19 -> -6136 | I20: =I18+I19 -> -6381.44 | ... K20: =K18+K19 -> -6902.1655
A21: CASH RECONCILIATION
A22: Net change in cash | B22: =B12+B16+B20 -> 1524 | C22: =C12+C16+C20 -> -1581 | D22: =D12+D16+D20 -> -86 | E22: =E12+E16+E20 -> 236 | F22: =F12+F16+F20 -> 25 | G22: =G12+G16+G20 -> -2163.0002 | H22: =H12+H16+H20 -> -418.36962 | I22: =I12+I16+I20 -> 810.63866 | ... K22: =K12+K16+K20 -> 2273.1916
A23: Cash, beginning of period | B23: ='Source Data'!$B$38 -> 3107 | C23: ='Balance Sheet'!B$6 -> 4631 | D23: ='Balance Sheet'!C$6 -> 3050 | E23: ='Balance Sheet'!D$6 -> 2964 | F23: ='Balance Sheet'!E$6 -> 3200 | G23: ='Balance Sheet'!$F$6 -> 3225 | H23: ='Balance Sheet'!G$6 -> 1061.9998 | I23: ='Balance Sheet'!H$6 -> 643.63014 | J23: ='Balance Sheet'!I$6 -> 1454.2688 | K23: ='Balance Sheet'!J$6 -> 3057.2282
A24: Cash, end of period | B24: =B23+B22 -> 4631 | C24: =C23+C22 -> 3050 | D24: =D23+D22 -> 2964 | E24: =E23+E22 -> 3200 | F24: =F23+F22 -> 3225 | G24: =G23+G22 -> 1061.9998 | H24: =H23+H22 -> 643.63014 | I24: =I23+I22 -> 1454.2688 | ... K24: =K23+K22 -> 5330.4197
A25: MEMO
A26: Memo: free cash flow (operating cash flow less capex) | B26: =B12+B14 -> 6294 | C26: =C12+C14 -> 5923 | D26: =D12+D14 -> 1349 | E26: =E12+E14 -> 1498 | F26: =F12+F14 -> 2603 | G26: =G12+G14 -> 3736.9998 | H26: =H12+H14 -> 5717.6304 | I26: =I12+I14 -> 7192.0787 | ... K26: =K12+K14 -> 9175.3571
A27: free cash flow margin % | B27: =B26/'Income Statement'!B$6 -> 0.34310946 | C27: =C26/'Income Statement'!C$6 -> 0.29573597 | D27: =D26/'Income Statement'!D$6 -> 0.077002112 | E27: =E26/'Income Statement'!E$6 -> 0.095773927 | F27: =F26/'Income Statement'!F$6 -> 0.14721185 | G27: =G26/'Income Statement'!G$6 -> 0.19213169 | H27: =H26/'Income Statement'!H$6 -> 0.27218755 | I27: =I26/'Income Statement'!I$6 -> 0.31997999 | ... K27: =K26/'Income Statement'!K$6 -> 0.36677203
A28: Memo: free cash flow after distributions | B28: =B26+B19 -> 2353 | C28: =C26+C19 -> -1389 | D28: =D26+D19 -> -2759 | E28: =E26+E19 -> -3748 | F28: =F26+F19 -> -3847 | G28: =G26+G19 -> -2163.0002 | H28: =H26+H19 -> -418.36962 | I28: =I26+I19 -> 810.63866 | ... K28: =K26+K19 -> 2273.1916 | M28: Negative means the dividend and buyback are being funded from the balance sheet rather than from cash generation.
A29: Memo: reported cash flow from operations (per filing) | B29: ='Source Data'!B$21 -> 8756 | C29: ='Source Data'!C$21 -> 8720 | D29: ='Source Data'!D$21 -> 6420 | E29: ='Source Data'!E$21 -> 6318 | F29: ='Source Data'!F$21 -> 7153 | G29: n/a | H29: n/a | I29: n/a | J29: n/a | K29: n/a

Sheet DCF
A1: Discounted Cash Flow Valuation
A2: Unlevered free cash flow, five-year explicit forecast plus a terminal value. Blue cells are inputs. The yellow cell needs a live share price before the upside line means anything.
A4: COST OF CAPITAL
A5: Risk-free rate | B5: 0.043 | M5: Long-bond yield. Input.
A6: Equity risk premium | B6: 0.05 | M6: Input.
A7: Levered beta | B7: 1.05 | M7: TI screens close to the market. Input.
A8: Cost of equity | B8: =B5+B7*B6 -> 0.0955
A9: Pre-tax cost of debt | B9: 0.05 | M9: Marginal new-issue rate, above the 3.9% blended coupon on the existing stack.
A10: Tax rate | B10: =Assumptions!$G$11 -> 0.14 | M10: Linked to the forecast effective tax rate on the Assumptions tab.
A11: After-tax cost of debt | B11: =B9*(1-B10) -> 0.043 | M11: The low effective tax rate means the interest shield is worth little.
A12: Target weight — equity | B12: 0.9 | M12: Target capital structure. Input, because the model has no market capitalisation until a price is entered below.
A13: Target weight — debt | B13: =1-B12 -> 0.1
A14: WACC | B14: =B12*B8+B13*B11 -> 0.09025
A16: VALUATION INPUTS
A17: Terminal growth rate | B17: 0.025 | M17: Roughly long-run nominal GDP. Input.
A18: Exit EV/EBITDA multiple (cross-check method) | B18: 12 | M18: Used only for the cross-check below, not for the headline.
A19: Mid-year convention (1 = on, 0 = off) | B19: 1 | M19: On by default: cash flows are assumed to arrive evenly through the year.
A20: Short-term investments treated as cash in the bridge | B20: 0 | M20: Default zero, i.e. only cash and equivalents are credited. TI held roughly $3.8bn of short-term investments and other current assets at FY2025 that are not separately tagged in the extract; crediting them would add about $4/share.
A21: Current share price | M21: ENTER THE LIVE PRICE. Not available in the source extract, so the upside line below reads n/a until this is filled in.
A23: UNLEVERED FREE CASH FLOW
A24: ($ in millions) | G24: FY2026E | H24: FY2027E | I24: FY2028E | J24: FY2029E | K24: FY2030E | M24: Notes
A25: Operating income (EBIT) | G25: ='Income Statement'!G$15 -> 7196.574 | H25: ='Income Statement'!H$15 -> 8360.474 | I25: ='Income Statement'!I$15 -> 9350.2869 | J25: ='Income Statement'!J$15 -> 10173.382 | K25: ='Income Statement'!K$15 -> 10932.216
A26: Less: tax on EBIT | G26: =-G25*Assumptions!G$11 -> -1007.5204 | H26: =-H25*Assumptions!H$11 -> -1170.4664 | I26: =-I25*Assumptions!I$11 -> -1309.0402 | J26: =-J25*Assumptions!J$11 -> -1424.2735 | K26: =-K25*Assumptions!K$11 -> -1530.5102
A27: NOPAT | G27: =G25+G26 -> 6189.0536 | H27: =H25+H26 -> 7190.0076 | I27: =I25+I26 -> 8041.2467 | J27: =J25+J26 -> 8749.1084 | K27: =K25+K26 -> 9401.7058
A28: Plus: depreciation and amortisation | G28: ='Cash Flow'!G$7 -> 1971.2 | H28: ='Cash Flow'!H$7 -> 2340.455 | I28: ='Cash Flow'!I$7 -> 2570.9613 | J28: ='Cash Flow'!J$7 -> 2699.0471 | K28: ='Cash Flow'!K$7 -> 2762.7648
A29: Less: capital expenditure | G29: ='Cash Flow'!G$14 -> -4279.044 | H29: ='Cash Flow'!H$14 -> -3781.1189 | I29: ='Cash Flow'!I$14 -> -3371.4977 | J29: ='Cash Flow'!J$14 -> -3097.2825 | K29: ='Cash Flow'!K$14 -> -3001.9815
A30: Less: increase in operating working capital | G30: =-('Balance Sheet'!G$29-'Balance Sheet'!F$29) -> -193.88024 | H30: =-('Balance Sheet'!H$29-'Balance Sheet'!G$29) -> -56.698665 | I30: =-('Balance Sheet'!I$29-'Balance Sheet'!H$29) -> -92.231676 | J30: =-('Balance Sheet'!J$29-'Balance Sheet'!I$29) -> -202.70245 | K30: =-('Balance Sheet'!K$29-'Balance Sheet'!J$29) -> -143.80007
A31: UNLEVERED FREE CASH FLOW | G31: =G27+G28+G29+G30 -> 3687.3294 | H31: =H27+H28+H29+H30 -> 5692.6451 | I31: =I27+I28+I29+I30 -> 7148.4786 | J31: =J27+J28+J29+J30 -> 8148.1705 | K31: =K27+K28+K29+K30 -> 9018.689
A32: Discount period (years) | G32: =1-0.5*$B$19 -> 0.5 | H32: =2-0.5*$B$19 -> 1.5 | I32: =3-0.5*$B$19 -> 2.5 | J32: =4-0.5*$B$19 -> 3.5 | K32: =5-0.5*$B$19 -> 4.5
A33: Discount factor | G33: =1/(1+$B$14)^G32 -> 0.95771646 | H33: =1/(1+$B$14)^H32 -> 0.87843748 | I33: =1/(1+$B$14)^I32 -> 0.80572115 | J33: =1/(1+$B$14)^J32 -> 0.73902421 | K33: =1/(1+$B$14)^K32 -> 0.67784839
A34: PV of unlevered free cash flow | G34: =G31*G33 -> 3531.4161 | H34: =H31*H33 -> 5000.6328 | I34: =I31*I33 -> 5759.6804 | J34: =J31*J33 -> 6021.6953 | K34: =K31*K33 -> 6113.3038
A36: ENTERPRISE AND EQUITY VALUE (Gordon growth terminal value — headline method)
A37: PV of explicit forecast free cash flow (FY2026E–FY2030E) | B37: =SUM(G34:K34) -> 26426.728
A38: Terminal value at FY2030E | B38: =K31*(1+B17)/(B14-B17) -> 141672.89
A39: PV of terminal value | B39: =B38*K33 -> 96032.742
A40: ENTERPRISE VALUE | B40: =B37+B39 -> 122459.47
A41: terminal value as % of enterprise value | B41: =B39/B40 -> 0.78420021 | M41: Above about 75% the answer is mostly an assumption about the terminal year, not about the forecast.
A42: Less: total debt (FY2025A) | B42: =-'Balance Sheet'!$F$27 -> -14048
A43: Plus: cash and equivalents (FY2025A) | B43: ='Balance Sheet'!$F$6 -> 3225
A44: Plus: short-term investments credited | B44: =B20 -> 0
A45: EQUITY VALUE | B45: =B40+B42+B43+B44 -> 111636.47
A46: Diluted shares outstanding (mm) | B46: ='Income Statement'!$F$26 -> 913
A47: VALUE PER SHARE | B47: =B45/B46 -> 122.27434
A48: Implied upside / (downside) vs current price | B48: =IF(B21="","n/a — enter a price above",B47/B21-1) -> n/a — enter a price above
A50: CROSS-CHECKS
A51: Implied exit EV/EBITDA embedded in the Gordon terminal value | B51: =B38/'Income Statement'!$K$30 -> 10.344877 | M51: If this is far from where analog semiconductors trade, the terminal growth rate is doing too much work.
A52: Terminal value on the exit-multiple method | B52: ='Income Statement'!$K$30*B18 -> 164339.77
A53: Enterprise value — exit-multiple method | B53: =B37+B52*K33 -> 137824.18
A54: Value per share — exit-multiple method | B54: =(B53+B42+B43+B44)/B46 -> 139.10315
A55: Perpetuity growth implied by the exit multiple | B55: =(B14*B52-K31)/(B52+K31) -> 0.033531535
A56: Enterprise value / FY2026E EBITDA | B56: =B40/'Income Statement'!$G$30 -> 13.357601
A57: Enterprise value / FY2025A EBITDA | B57: =B40/'Income Statement'!$F$30 -> 15.421165
A58: Implied enterprise value at the current share price | B58: =IF(B21="","n/a",B21*B46-B42-B43-B44) -> n/a
A60: SENSITIVITY — VALUE PER SHARE: WACC (rows) vs TERMINAL GROWTH (columns)
A61: WACC \ terminal growth | B61: 0.015 | C61: 0.02 | D61: 0.025 | E61: 0.03 | F61: 0.035
A62: 0.075 | B62: =IF($A62-B$61<0.01,"n/m",((G$31/(1+$A62)^G$32+H$31/(1+$A62)^H$32+I$31/(1+$A62)^I$32+J$31/(1+$A62)^J$32+K$31/(1+$A62)^K$32)+(K$31*(1+B$61)/($A62-B$61))/(1+$A62)^K$32+$B$42+$B$43+$B$44)/$B$46) -> 138.91643 | C62: =IF($A62-C$61<0.01,"n/m",((G$31/(1+$A62)^G$32+H$31/(1+$A62)^H$32+I$31/(1+$A62)^I$32+J$31/(1+$A62)^J$32+K$31/(1+$A62)^K$32)+(K$31*(1+C$61)/($A62-C$61))/(1+$A62)^K$32+$B$42+$B$43+$B$44)/$B$46) -> 150.53624 | D62: =IF($A62-D$61<0.01,"n/m",((G$31/(1+$A62)^G$32+H$31/(1+$A62)^H$32+I$31/(1+$A62)^I$32+J$31/(1+$A62)^J$32+K$31/(1+$A62)^K$32)+(K$31*(1+D$61)/($A62-D$61))/(1+$A62)^K$32+$B$42+$B$43+$B$44)/$B$46) -> 164.48002 | E62: =IF($A62-E$61<0.01,"n/m",((G$31/(1+$A62)^G$32+H$31/(1+$A62)^H$32+I$31/(1+$A62)^I$32+J$31/(1+$A62)^J$32+K$31/(1+$A62)^K$32)+(K$31*(1+E$61)/($A62-E$61))/(1+$A62)^K$32+$B$42+$B$43+$B$44)/$B$46) -> 181.52241 | F62: =IF($A62-F$61<0.01,"n/m",((G$31/(1+$A62)^G$32+H$31/(1+$A62)^H$32+I$31/(1+$A62)^I$32+J$31/(1+$A62)^J$32+K$31/(1+$A62)^K$32)+(K$31*(1+F$61)/($A62-F$61))/(1+$A62)^K$32+$B$42+$B$43+$B$44)/$B$46) -> 202.82539 | M62: Each cell re-discounts the full five-year forecast and rebuilds the terminal value at that WACC and growth rate — these are live formulas, not a pasted data table.
A63: 0.08 | B63: =IF($A63-B$61<0.01,"n/m",((G$31/(1+$A63)^G$32+H$31/(1+$A63)^H$32+I$31/(1+$A63)^I$32+J$31/(1+$A63)^J$32+K$31/(1+$A63)^K$32)+(K$31*(1+B$61)/($A63-B$61))/(1+$A63)^K$32+$B$42+$B$43+$B$44)/$B$46) -> 126.94869 | C63: =IF($A63-C$61<0.01,"n/m",((G$31/(1+$A63)^G$32+H$31/(1+$A63)^H$32+I$31/(1+$A63)^I$32+J$31/(1+$A63)^J$32+K$31/(1+$A63)^K$32)+(K$31*(1+C$61)/($A63-C$61))/(1+$A63)^K$32+$B$42+$B$43+$B$44)/$B$46) -> 136.62244 | D63: =IF($A63-D$61<0.01,"n/m",((G$31/(1+$A63)^G$32+H$31/(1+$A63)^H$32+I$31/(1+$A63)^I$32+J$31/(1+$A63)^J$32+K$31/(1+$A63)^K$32)+(K$31*(1+D$61)/($A63-D$61))/(1+$A63)^K$32+$B$42+$B$43+$B$44)/$B$46) -> 148.05506 | E63: =IF($A63-E$61<0.01,"n/m",((G$31/(1+$A63)^G$32+H$31/(1+$A63)^H$32+I$31/(1+$A63)^I$32+J$31/(1+$A63)^J$32+K$31/(1+$A63)^K$32)+(K$31*(1+E$61)/($A63-E$61))/(1+$A63)^K$32+$B$42+$B$43+$B$44)/$B$46) -> 161.77419 | F63: =IF($A63-F$61<0.01,"n/m",((G$31/(1+$A63)^G$32+H$31/(1+$A63)^H$32+I$31/(1+$A63)^I$32+J$31/(1+$A63)^J$32+K$31/(1+$A63)^K$32)+(K$31*(1+F$61)/($A63-F$61))/(1+$A63)^K$32+$B$42+$B$43+$B$44)/$B$46) -> 178.54203
A64: 0.085 | B64: =IF($A64-B$61<0.01,"n/m",((G$31/(1+$A64)^G$32+H$31/(1+$A64)^H$32+I$31/(1+$A64)^I$32+J$31/(1+$A64)^J$32+K$31/(1+$A64)^K$32)+(K$31*(1+B$61)/($A64-B$61))/(1+$A64)^K$32+$B$42+$B$43+$B$44)/$B$46) -> 116.69749 | C64: =IF($A64-C$61<0.01,"n/m",((G$31/(1+$A64)^G$32+H$31/(1+$A64)^H$32+I$31/(1+$A64)^I$32+J$31/(1+$A64)^J$32+K$31/(1+$A64)^K$32)+(K$31*(1+C$61)/($A64-C$61))/(1+$A64)^K$32+$B$42+$B$43+$B$44)/$B$46) -> 124.85631 | D64: =IF($A64-D$61<0.01,"n/m",((G$31/(1+$A64)^G$32+H$31/(1+$A64)^H$32+I$31/(1+$A64)^I$32+J$31/(1+$A64)^J$32+K$31/(1+$A64)^K$32)+(K$31*(1+D$61)/($A64-D$61))/(1+$A64)^K$32+$B$42+$B$43+$B$44)/$B$46) -> 134.37493 | E64: =IF($A64-E$61<0.01,"n/m",((G$31/(1+$A64)^G$32+H$31/(1+$A64)^H$32+I$31/(1+$A64)^I$32+J$31/(1+$A64)^J$32+K$31/(1+$A64)^K$32)+(K$31*(1+E$61)/($A64-E$61))/(1+$A64)^K$32+$B$42+$B$43+$B$44)/$B$46) -> 145.62421 | F64: =IF($A64-F$61<0.01,"n/m",((G$31/(1+$A64)^G$32+H$31/(1+$A64)^H$32+I$31/(1+$A64)^I$32+J$31/(1+$A64)^J$32+K$31/(1+$A64)^K$32)+(K$31*(1+F$61)/($A64-F$61))/(1+$A64)^K$32+$B$42+$B$43+$B$44)/$B$46) -> 159.12334
A65: 0.09 | B65: =IF($A65-B$61<0.01,"n/m",((G$31/(1+$A65)^G$32+H$31/(1+$A65)^H$32+I$31/(1+$A65)^I$32+J$31/(1+$A65)^J$32+K$31/(1+$A65)^K$32)+(K$31*(1+B$61)/($A65-B$61))/(1+$A65)^K$32+$B$42+$B$43+$B$44)/$B$46) -> 107.81939 | C65: =IF($A65-C$61<0.01,"n/m",((G$31/(1+$A65)^G$32+H$31/(1+$A65)^H$32+I$31/(1+$A65)^I$32+J$31/(1+$A65)^J$32+K$31/(1+$A65)^K$32)+(K$31*(1+C$61)/($A65-C$61))/(1+$A65)^K$32+$B$42+$B$43+$B$44)/$B$46) -> 114.77749 | D65: =IF($A65-D$61<0.01,"n/m",((G$31/(1+$A65)^G$32+H$31/(1+$A65)^H$32+I$31/(1+$A65)^I$32+J$31/(1+$A65)^J$32+K$31/(1+$A65)^K$32)+(K$31*(1+D$61)/($A65-D$61))/(1+$A65)^K$32+$B$42+$B$43+$B$44)/$B$46) -> 122.80607 | E65: =IF($A65-E$61<0.01,"n/m",((G$31/(1+$A65)^G$32+H$31/(1+$A65)^H$32+I$31/(1+$A65)^I$32+J$31/(1+$A65)^J$32+K$31/(1+$A65)^K$32)+(K$31*(1+E$61)/($A65-E$61))/(1+$A65)^K$32+$B$42+$B$43+$B$44)/$B$46) -> 132.17274 | F65: =IF($A65-F$61<0.01,"n/m",((G$31/(1+$A65)^G$32+H$31/(1+$A65)^H$32+I$31/(1+$A65)^I$32+J$31/(1+$A65)^J$32+K$31/(1+$A65)^K$32)+(K$31*(1+F$61)/($A65-F$61))/(1+$A65)^K$32+$B$42+$B$43+$B$44)/$B$46) -> 143.24244
A66: 0.095 | B66: =IF($A66-B$61<0.01,"n/m",((G$31/(1+$A66)^G$32+H$31/(1+$A66)^H$32+I$31/(1+$A66)^I$32+J$31/(1+$A66)^J$32+K$31/(1+$A66)^K$32)+(K$31*(1+B$61)/($A66-B$61))/(1+$A66)^K$32+$B$42+$B$43+$B$44)/$B$46) -> 100.05681 | C66: =IF($A66-C$61<0.01,"n/m",((G$31/(1+$A66)^G$32+H$31/(1+$A66)^H$32+I$31/(1+$A66)^I$32+J$31/(1+$A66)^J$32+K$31/(1+$A66)^K$32)+(K$31*(1+C$61)/($A66-C$61))/(1+$A66)^K$32+$B$42+$B$43+$B$44)/$B$46) -> 106.0484 | D66: =IF($A66-D$61<0.01,"n/m",((G$31/(1+$A66)^G$32+H$31/(1+$A66)^H$32+I$31/(1+$A66)^I$32+J$31/(1+$A66)^J$32+K$31/(1+$A66)^K$32)+(K$31*(1+D$61)/($A66-D$61))/(1+$A66)^K$32+$B$42+$B$43+$B$44)/$B$46) -> 112.89593 | E66: =IF($A66-E$61<0.01,"n/m",((G$31/(1+$A66)^G$32+H$31/(1+$A66)^H$32+I$31/(1+$A66)^I$32+J$31/(1+$A66)^J$32+K$31/(1+$A66)^K$32)+(K$31*(1+E$61)/($A66-E$61))/(1+$A66)^K$32+$B$42+$B$43+$B$44)/$B$46) -> 120.79692 | F66: =IF($A66-F$61<0.01,"n/m",((G$31/(1+$A66)^G$32+H$31/(1+$A66)^H$32+I$31/(1+$A66)^I$32+J$31/(1+$A66)^J$32+K$31/(1+$A66)^K$32)+(K$31*(1+F$61)/($A66-F$61))/(1+$A66)^K$32+$B$42+$B$43+$B$44)/$B$46) -> 130.01475
A67: 0.1 | B67: =IF($A67-B$61<0.01,"n/m",((G$31/(1+$A67)^G$32+H$31/(1+$A67)^H$32+I$31/(1+$A67)^I$32+J$31/(1+$A67)^J$32+K$31/(1+$A67)^K$32)+(K$31*(1+B$61)/($A67-B$61))/(1+$A67)^K$32+$B$42+$B$43+$B$44)/$B$46) -> 93.212767 | C67: =IF($A67-C$61<0.01,"n/m",((G$31/(1+$A67)^G$32+H$31/(1+$A67)^H$32+I$31/(1+$A67)^I$32+J$31/(1+$A67)^J$32+K$31/(1+$A67)^K$32)+(K$31*(1+C$61)/($A67-C$61))/(1+$A67)^K$32+$B$42+$B$43+$B$44)/$B$46) -> 98.415833 | D67: =IF($A67-D$61<0.01,"n/m",((G$31/(1+$A67)^G$32+H$31/(1+$A67)^H$32+I$31/(1+$A67)^I$32+J$31/(1+$A67)^J$32+K$31/(1+$A67)^K$32)+(K$31*(1+D$61)/($A67-D$61))/(1+$A67)^K$32+$B$42+$B$43+$B$44)/$B$46) -> 104.31264 | E67: =IF($A67-E$61<0.01,"n/m",((G$31/(1+$A67)^G$32+H$31/(1+$A67)^H$32+I$31/(1+$A67)^I$32+J$31/(1+$A67)^J$32+K$31/(1+$A67)^K$32)+(K$31*(1+E$61)/($A67-E$61))/(1+$A67)^K$32+$B$42+$B$43+$B$44)/$B$46) -> 111.05185 | F67: =IF($A67-F$61<0.01,"n/m",((G$31/(1+$A67)^G$32+H$31/(1+$A67)^H$32+I$31/(1+$A67)^I$32+J$31/(1+$A67)^J$32+K$31/(1+$A67)^K$32)+(K$31*(1+F$61)/($A67-F$61))/(1+$A67)^K$32+$B$42+$B$43+$B$44)/$B$46) -> 118.82786
A68: 0.105 | B68: =IF($A68-B$61<0.01,"n/m",((G$31/(1+$A68)^G$32+H$31/(1+$A68)^H$32+I$31/(1+$A68)^I$32+J$31/(1+$A68)^J$32+K$31/(1+$A68)^K$32)+(K$31*(1+B$61)/($A68-B$61))/(1+$A68)^K$32+$B$42+$B$43+$B$44)/$B$46) -> 87.134073 | C68: =IF($A68-C$61<0.01,"n/m",((G$31/(1+$A68)^G$32+H$31/(1+$A68)^H$32+I$31/(1+$A68)^I$32+J$31/(1+$A68)^J$32+K$31/(1+$A68)^K$32)+(K$31*(1+C$61)/($A68-C$61))/(1+$A68)^K$32+$B$42+$B$43+$B$44)/$B$46) -> 91.686188 | D68: =IF($A68-D$61<0.01,"n/m",((G$31/(1+$A68)^G$32+H$31/(1+$A68)^H$32+I$31/(1+$A68)^I$32+J$31/(1+$A68)^J$32+K$31/(1+$A68)^K$32)+(K$31*(1+D$61)/($A68-D$61))/(1+$A68)^K$32+$B$42+$B$43+$B$44)/$B$46) -> 96.807317 | E68: =IF($A68-E$61<0.01,"n/m",((G$31/(1+$A68)^G$32+H$31/(1+$A68)^H$32+I$31/(1+$A68)^I$32+J$31/(1+$A68)^J$32+K$31/(1+$A68)^K$32)+(K$31*(1+E$61)/($A68-E$61))/(1+$A68)^K$32+$B$42+$B$43+$B$44)/$B$46) -> 102.61126 | F68: =IF($A68-F$61<0.01,"n/m",((G$31/(1+$A68)^G$32+H$31/(1+$A68)^H$32+I$31/(1+$A68)^I$32+J$31/(1+$A68)^J$32+K$31/(1+$A68)^K$32)+(K$31*(1+F$61)/($A68-F$61))/(1+$A68)^K$32+$B$42+$B$43+$B$44)/$B$46) -> 109.24435
A70: SENSITIVITY — VALUE PER SHARE: WACC (rows) vs EXIT EV/EBITDA MULTIPLE (columns)
A71: WACC \ exit multiple | B71: 9 | C71: 10.5 | D71: 12 | E71: 13.5 | F71: 15
A72: 0.075 | B72: =((G$31/(1+$A72)^G$32+H$31/(1+$A72)^H$32+I$31/(1+$A72)^I$32+J$31/(1+$A72)^J$32+K$31/(1+$A72)^K$32)+('Income Statement'!$K$30*B$71)/(1+$A72)^K$32+$B$42+$B$43+$B$44)/$B$46 -> 115.73039 | C72: =((G$31/(1+$A72)^G$32+H$31/(1+$A72)^H$32+I$31/(1+$A72)^I$32+J$31/(1+$A72)^J$32+K$31/(1+$A72)^K$32)+('Income Statement'!$K$30*C$71)/(1+$A72)^K$32+$B$42+$B$43+$B$44)/$B$46 -> 131.98003 | D72: =((G$31/(1+$A72)^G$32+H$31/(1+$A72)^H$32+I$31/(1+$A72)^I$32+J$31/(1+$A72)^J$32+K$31/(1+$A72)^K$32)+('Income Statement'!$K$30*D$71)/(1+$A72)^K$32+$B$42+$B$43+$B$44)/$B$46 -> 148.22968 | E72: =((G$31/(1+$A72)^G$32+H$31/(1+$A72)^H$32+I$31/(1+$A72)^I$32+J$31/(1+$A72)^J$32+K$31/(1+$A72)^K$32)+('Income Statement'!$K$30*E$71)/(1+$A72)^K$32+$B$42+$B$43+$B$44)/$B$46 -> 164.47932 | F72: =((G$31/(1+$A72)^G$32+H$31/(1+$A72)^H$32+I$31/(1+$A72)^I$32+J$31/(1+$A72)^J$32+K$31/(1+$A72)^K$32)+('Income Statement'!$K$30*F$71)/(1+$A72)^K$32+$B$42+$B$43+$B$44)/$B$46 -> 180.72896
A73: 0.08 | B73: =((G$31/(1+$A73)^G$32+H$31/(1+$A73)^H$32+I$31/(1+$A73)^I$32+J$31/(1+$A73)^J$32+K$31/(1+$A73)^K$32)+('Income Statement'!$K$30*B$71)/(1+$A73)^K$32+$B$42+$B$43+$B$44)/$B$46 -> 113.33333 | C73: =((G$31/(1+$A73)^G$32+H$31/(1+$A73)^H$32+I$31/(1+$A73)^I$32+J$31/(1+$A73)^J$32+K$31/(1+$A73)^K$32)+('Income Statement'!$K$30*C$71)/(1+$A73)^K$32+$B$42+$B$43+$B$44)/$B$46 -> 129.24717 | D73: =((G$31/(1+$A73)^G$32+H$31/(1+$A73)^H$32+I$31/(1+$A73)^I$32+J$31/(1+$A73)^J$32+K$31/(1+$A73)^K$32)+('Income Statement'!$K$30*D$71)/(1+$A73)^K$32+$B$42+$B$43+$B$44)/$B$46 -> 145.16101 | E73: =((G$31/(1+$A73)^G$32+H$31/(1+$A73)^H$32+I$31/(1+$A73)^I$32+J$31/(1+$A73)^J$32+K$31/(1+$A73)^K$32)+('Income Statement'!$K$30*E$71)/(1+$A73)^K$32+$B$42+$B$43+$B$44)/$B$46 -> 161.07485 | F73: =((G$31/(1+$A73)^G$32+H$31/(1+$A73)^H$32+I$31/(1+$A73)^I$32+J$31/(1+$A73)^J$32+K$31/(1+$A73)^K$32)+('Income Statement'!$K$30*F$71)/(1+$A73)^K$32+$B$42+$B$43+$B$44)/$B$46 -> 176.98869
A74: 0.085 | B74: =((G$31/(1+$A74)^G$32+H$31/(1+$A74)^H$32+I$31/(1+$A74)^I$32+J$31/(1+$A74)^J$32+K$31/(1+$A74)^K$32)+('Income Statement'!$K$30*B$71)/(1+$A74)^K$32+$B$42+$B$43+$B$44)/$B$46 -> 110.99465 | C74: =((G$31/(1+$A74)^G$32+H$31/(1+$A74)^H$32+I$31/(1+$A74)^I$32+J$31/(1+$A74)^J$32+K$31/(1+$A74)^K$32)+('Income Statement'!$K$30*C$71)/(1+$A74)^K$32+$B$42+$B$43+$B$44)/$B$46 -> 126.58113 | D74: =((G$31/(1+$A74)^G$32+H$31/(1+$A74)^H$32+I$31/(1+$A74)^I$32+J$31/(1+$A74)^J$32+K$31/(1+$A74)^K$32)+('Income Statement'!$K$30*D$71)/(1+$A74)^K$32+$B$42+$B$43+$B$44)/$B$46 -> 142.16761 | E74: =((G$31/(1+$A74)^G$32+H$31/(1+$A74)^H$32+I$31/(1+$A74)^I$32+J$31/(1+$A74)^J$32+K$31/(1+$A74)^K$32)+('Income Statement'!$K$30*E$71)/(1+$A74)^K$32+$B$42+$B$43+$B$44)/$B$46 -> 157.75409 | F74: =((G$31/(1+$A74)^G$32+H$31/(1+$A74)^H$32+I$31/(1+$A74)^I$32+J$31/(1+$A74)^J$32+K$31/(1+$A74)^K$32)+('Income Statement'!$K$30*F$71)/(1+$A74)^K$32+$B$42+$B$43+$B$44)/$B$46 -> 173.34058
A75: 0.09 | B75: =((G$31/(1+$A75)^G$32+H$31/(1+$A75)^H$32+I$31/(1+$A75)^I$32+J$31/(1+$A75)^J$32+K$31/(1+$A75)^K$32)+('Income Statement'!$K$30*B$71)/(1+$A75)^K$32+$B$42+$B$43+$B$44)/$B$46 -> 108.71266 | C75: =((G$31/(1+$A75)^G$32+H$31/(1+$A75)^H$32+I$31/(1+$A75)^I$32+J$31/(1+$A75)^J$32+K$31/(1+$A75)^K$32)+('Income Statement'!$K$30*C$71)/(1+$A75)^K$32+$B$42+$B$43+$B$44)/$B$46 -> 123.97997 | D75: =((G$31/(1+$A75)^G$32+H$31/(1+$A75)^H$32+I$31/(1+$A75)^I$32+J$31/(1+$A75)^J$32+K$31/(1+$A75)^K$32)+('Income Statement'!$K$30*D$71)/(1+$A75)^K$32+$B$42+$B$43+$B$44)/$B$46 -> 139.24729 | E75: =((G$31/(1+$A75)^G$32+H$31/(1+$A75)^H$32+I$31/(1+$A75)^I$32+J$31/(1+$A75)^J$32+K$31/(1+$A75)^K$32)+('Income Statement'!$K$30*E$71)/(1+$A75)^K$32+$B$42+$B$43+$B$44)/$B$46 -> 154.5146 | F75: =((G$31/(1+$A75)^G$32+H$31/(1+$A75)^H$32+I$31/(1+$A75)^I$32+J$31/(1+$A75)^J$32+K$31/(1+$A75)^K$32)+('Income Statement'!$K$30*F$71)/(1+$A75)^K$32+$B$42+$B$43+$B$44)/$B$46 -> 169.78192
A76: 0.095 | B76: =((G$31/(1+$A76)^G$32+H$31/(1+$A76)^H$32+I$31/(1+$A76)^I$32+J$31/(1+$A76)^J$32+K$31/(1+$A76)^K$32)+('Income Statement'!$K$30*B$71)/(1+$A76)^K$32+$B$42+$B$43+$B$44)/$B$46 -> 106.48571 | C76: =((G$31/(1+$A76)^G$32+H$31/(1+$A76)^H$32+I$31/(1+$A76)^I$32+J$31/(1+$A76)^J$32+K$31/(1+$A76)^K$32)+('Income Statement'!$K$30*C$71)/(1+$A76)^K$32+$B$42+$B$43+$B$44)/$B$46 -> 121.44181 | D76: =((G$31/(1+$A76)^G$32+H$31/(1+$A76)^H$32+I$31/(1+$A76)^I$32+J$31/(1+$A76)^J$32+K$31/(1+$A76)^K$32)+('Income Statement'!$K$30*D$71)/(1+$A76)^K$32+$B$42+$B$43+$B$44)/$B$46 -> 136.39791 | E76: =((G$31/(1+$A76)^G$32+H$31/(1+$A76)^H$32+I$31/(1+$A76)^I$32+J$31/(1+$A76)^J$32+K$31/(1+$A76)^K$32)+('Income Statement'!$K$30*E$71)/(1+$A76)^K$32+$B$42+$B$43+$B$44)/$B$46 -> 151.35401 | F76: =((G$31/(1+$A76)^G$32+H$31/(1+$A76)^H$32+I$31/(1+$A76)^I$32+J$31/(1+$A76)^J$32+K$31/(1+$A76)^K$32)+('Income Statement'!$K$30*F$71)/(1+$A76)^K$32+$B$42+$B$43+$B$44)/$B$46 -> 166.31011
A77: 0.1 | B77: =((G$31/(1+$A77)^G$32+H$31/(1+$A77)^H$32+I$31/(1+$A77)^I$32+J$31/(1+$A77)^J$32+K$31/(1+$A77)^K$32)+('Income Statement'!$K$30*B$71)/(1+$A77)^K$32+$B$42+$B$43+$B$44)/$B$46 -> 104.31222 | C77: =((G$31/(1+$A77)^G$32+H$31/(1+$A77)^H$32+I$31/(1+$A77)^I$32+J$31/(1+$A77)^J$32+K$31/(1+$A77)^K$32)+('Income Statement'!$K$30*C$71)/(1+$A77)^K$32+$B$42+$B$43+$B$44)/$B$46 -> 118.96483 | D77: =((G$31/(1+$A77)^G$32+H$31/(1+$A77)^H$32+I$31/(1+$A77)^I$32+J$31/(1+$A77)^J$32+K$31/(1+$A77)^K$32)+('Income Statement'!$K$30*D$71)/(1+$A77)^K$32+$B$42+$B$43+$B$44)/$B$46 -> 133.61743 | E77: =((G$31/(1+$A77)^G$32+H$31/(1+$A77)^H$32+I$31/(1+$A77)^I$32+J$31/(1+$A77)^J$32+K$31/(1+$A77)^K$32)+('Income Statement'!$K$30*E$71)/(1+$A77)^K$32+$B$42+$B$43+$B$44)/$B$46 -> 148.27003 | F77: =((G$31/(1+$A77)^G$32+H$31/(1+$A77)^H$32+I$31/(1+$A77)^I$32+J$31/(1+$A77)^J$32+K$31/(1+$A77)^K$32)+('Income Statement'!$K$30*F$71)/(1+$A77)^K$32+$B$42+$B$43+$B$44)/$B$46 -> 162.92264
A78: 0.105 | B78: =((G$31/(1+$A78)^G$32+H$31/(1+$A78)^H$32+I$31/(1+$A78)^I$32+J$31/(1+$A78)^J$32+K$31/(1+$A78)^K$32)+('Income Statement'!$K$30*B$71)/(1+$A78)^K$32+$B$42+$B$43+$B$44)/$B$46 -> 102.19066 | C78: =((G$31/(1+$A78)^G$32+H$31/(1+$A78)^H$32+I$31/(1+$A78)^I$32+J$31/(1+$A78)^J$32+K$31/(1+$A78)^K$32)+('Income Statement'!$K$30*C$71)/(1+$A78)^K$32+$B$42+$B$43+$B$44)/$B$46 -> 116.54726 | D78: =((G$31/(1+$A78)^G$32+H$31/(1+$A78)^H$32+I$31/(1+$A78)^I$32+J$31/(1+$A78)^J$32+K$31/(1+$A78)^K$32)+('Income Statement'!$K$30*D$71)/(1+$A78)^K$32+$B$42+$B$43+$B$44)/$B$46 -> 130.90386 | E78: =((G$31/(1+$A78)^G$32+H$31/(1+$A78)^H$32+I$31/(1+$A78)^I$32+J$31/(1+$A78)^J$32+K$31/(1+$A78)^K$32)+('Income Statement'!$K$30*E$71)/(1+$A78)^K$32+$B$42+$B$43+$B$44)/$B$46 -> 145.26046 | F78: =((G$31/(1+$A78)^G$32+H$31/(1+$A78)^H$32+I$31/(1+$A78)^I$32+J$31/(1+$A78)^J$32+K$31/(1+$A78)^K$32)+('Income Statement'!$K$30*F$71)/(1+$A78)^K$32+$B$42+$B$43+$B$44)/$B$46 -> 159.61706

Sheet Checks
A1: Integrity Checks and Data-Quality Flags
A2: Every figure below is a live formula. Anything other than "OK" needs looking at before the model is used.
A4: Check | B4: FY2021A | C4: FY2022A | D4: FY2023A | E4: FY2024A | F4: FY2025A | G4: FY2026E | H4: FY2027E | I4: FY2028E | J4: FY2029E | K4: FY2030E | L4: Status | M4: Notes
A5: SOURCE DATA INTEGRITY (tests run on the raw extract, not on the model)
A6: Assets less liabilities and equity, as reported | B6: ='Source Data'!B$28-'Source Data'!B$33-'Source Data'!B$34 -> 0 | C6: ='Source Data'!C$28-'Source Data'!C$33-'Source Data'!C$34 -> 0 | D6: ='Source Data'!D$28-'Source Data'!D$33-'Source Data'!D$34 -> 0 | E6: ='Source Data'!E$28-'Source Data'!E$33-'Source Data'!E$34 -> 0 | F6: ='Source Data'!F$28-'Source Data'!F$33-'Source Data'!F$34 -> 0 | L6: =IF(ABS(B6)+ABS(C6)+ABS(D6)+ABS(E6)+ABS(F6)<2.5,"OK","CHECK") -> OK
A7: Revenue less cost of revenue, less reported gross profit | B7: ='Source Data'!B$7-'Source Data'!B$8-'Source Data'!B$9 -> 0 | C7: ='Source Data'!C$7-'Source Data'!C$8-'Source Data'!C$9 -> 0 | D7: ='Source Data'!D$7-'Source Data'!D$8-'Source Data'!D$9 -> 0 | E7: ='Source Data'!E$7-'Source Data'!E$8-'Source Data'!E$9 -> 0 | F7: ='Source Data'!F$7-'Source Data'!F$8-'Source Data'!F$9 -> 0 | L7: =IF(ABS(B7)+ABS(C7)+ABS(D7)+ABS(E7)+ABS(F7)<2.5,"OK","CHECK") -> OK
A8: Pre-tax income less tax, less reported net income | B8: ='Source Data'!B$14-'Source Data'!B$15-'Source Data'!B$16 -> 0 | C8: ='Source Data'!C$14-'Source Data'!C$15-'Source Data'!C$16 -> 0 | D8: ='Source Data'!D$14-'Source Data'!D$15-'Source Data'!D$16 -> 0 | E8: ='Source Data'!E$14-'Source Data'!E$15-'Source Data'!E$16 -> 0 | F8: ='Source Data'!F$14-'Source Data'!F$15-'Source Data'!F$16 -> 0 | L8: =IF(ABS(B8)+ABS(C8)+ABS(D8)+ABS(E8)+ABS(F8)<2.5,"OK","CHECK") -> OK
A9: MODEL INTEGRITY
A10: Balance sheet: total assets less total liabilities and equity | B10: ='Balance Sheet'!B$25 -> 0 | C10: ='Balance Sheet'!C$25 -> 0 | D10: ='Balance Sheet'!D$25 -> 0 | E10: ='Balance Sheet'!E$25 -> 0 | F10: ='Balance Sheet'!F$25 -> 0 | G10: ='Balance Sheet'!G$25 -> 0 | H10: ='Balance Sheet'!H$25 -> 0 | I10: ='Balance Sheet'!I$25 -> 0 | ... K10: ='Balance Sheet'!K$25 -> 0 | L10: =IF(ABS(B10)+ABS(C10)+ABS(D10)+ABS(E10)+ABS(F10)+ABS(G10)+ABS(H10)+ABS(I10)+ABS(J10)+ABS(K10)<5,"OK","CHECK") -> OK
A11: Modelled operating income less reported operating income | B11: ='Income Statement'!B$15-'Source Data'!B$12 -> 0 | C11: ='Income Statement'!C$15-'Source Data'!C$12 -> 0 | D11: ='Income Statement'!D$15-'Source Data'!D$12 -> 0 | E11: ='Income Statement'!E$15-'Source Data'!E$12 -> 0 | F11: ='Income Statement'!F$15-'Source Data'!F$12 -> 0 | L11: =IF(ABS(B11)+ABS(C11)+ABS(D11)+ABS(E11)+ABS(F11)<2.5,"OK","CHECK") -> OK
A12: Modelled pre-tax income less reported pre-tax income | B12: ='Income Statement'!B$20-'Source Data'!B$14 -> 0 | C12: ='Income Statement'!C$20-'Source Data'!C$14 -> 0 | D12: ='Income Statement'!D$20-'Source Data'!D$14 -> 0 | E12: ='Income Statement'!E$20-'Source Data'!E$14 -> 0 | F12: ='Income Statement'!F$20-'Source Data'!F$14 -> 0 | L12: =IF(ABS(B12)+ABS(C12)+ABS(D12)+ABS(E12)+ABS(F12)<2.5,"OK","CHECK") -> OK
A13: Modelled operating cash flow less reported operating cash flow | B13: ='Cash Flow'!B$12-'Source Data'!B$21 -> 0 | C13: ='Cash Flow'!C$12-'Source Data'!C$21 -> 0 | D13: ='Cash Flow'!D$12-'Source Data'!D$21 -> 0 | E13: ='Cash Flow'!E$12-'Source Data'!E$21 -> 0 | F13: ='Cash Flow'!F$12-'Source Data'!F$21 -> 0 | L13: =IF(ABS(B13)+ABS(C13)+ABS(D13)+ABS(E13)+ABS(F13)<2.5,"OK","CHECK") -> OK
A14: Cash flow closing cash less balance sheet cash | B14: ='Cash Flow'!B$24-'Balance Sheet'!B$6 -> 0 | C14: ='Cash Flow'!C$24-'Balance Sheet'!C$6 -> 0 | D14: ='Cash Flow'!D$24-'Balance Sheet'!D$6 -> 0 | E14: ='Cash Flow'!E$24-'Balance Sheet'!E$6 -> 0 | F14: ='Cash Flow'!F$24-'Balance Sheet'!F$6 -> 0 | G14: ='Cash Flow'!G$24-'Balance Sheet'!G$6 -> 0 | H14: ='Cash Flow'!H$24-'Balance Sheet'!H$6 -> 0 | I14: ='Cash Flow'!I$24-'Balance Sheet'!I$6 -> 0 | ... K14: ='Cash Flow'!K$24-'Balance Sheet'!K$6 -> 0 | L14: =IF(ABS(B14)+ABS(C14)+ABS(D14)+ABS(E14)+ABS(F14)+ABS(G14)+ABS(H14)+ABS(I14)+ABS(J14)+ABS(K14)<5,"OK","CHECK") -> OK
A15: SANITY FLAGS (not errors — judgement calls to be aware of)
A16: Closing cash versus the minimum operating cash assumption | G16: ='Balance Sheet'!G$6-Assumptions!$B$35 -> 61.999759 | H16: ='Balance Sheet'!H$6-Assumptions!$B$35 -> -356.36986 | I16: ='Balance Sheet'!I$6-Assumptions!$B$35 -> 454.2688 | J16: ='Balance Sheet'!J$6-Assumptions!$B$35 -> 2057.2282 | K16: ='Balance Sheet'!K$6-Assumptions!$B$35 -> 4330.4197 | L16: =IF(MIN(G16:K16)<0,"FLAG","OK") -> FLAG | M16: Cash is the balancing item and there is no revolver in the model. A negative figure means the assumed distributions cannot be funded from cash generation in that year.
A17: Free cash flow after shareholder distributions | B17: ='Cash Flow'!B$28 -> 2353 | C17: ='Cash Flow'!C$28 -> -1389 | D17: ='Cash Flow'!D$28 -> -2759 | E17: ='Cash Flow'!E$28 -> -3748 | F17: ='Cash Flow'!F$28 -> -3847 | G17: ='Cash Flow'!G$28 -> -2163.0002 | H17: ='Cash Flow'!H$28 -> -418.36962 | I17: ='Cash Flow'!I$28 -> 810.63866 | ... K17: ='Cash Flow'!K$28 -> 2273.1916 | L17: =IF(MIN(G17:K17)<0,"FLAG","OK") -> FLAG | M17: Negative in FY2021 through FY2025 as well — the fab programme and the dividend were part-funded with debt.
A18: Terminal value as a share of enterprise value | B18: =DCF!$B$41 -> 0.78420021 | L18: =IF(B18>0.8,"FLAG","OK") -> OK | M18: Above 80% the valuation is dominated by the terminal assumption.
A19: Gross margin in FY2030E versus the FY2022 peak | B19: ='Income Statement'!$K$10-'Income Statement'!$C$10 -> -0.067587378 | L19: =IF(B19>0,"FLAG","OK") -> OK | M19: A flag here would mean the forecast assumes margins beat the cyclical peak.
A21: DATA-QUALITY FLAGS FROM THE SOURCE EXTRACT
A22: Flag | B22: Detail
A23: 1. Dividends and buybacks are absent from the extract. | B23: The extract has no financing cash flows at all. Historical shareholder distributions on the Assumptions tab are DERIVED from the equity roll-forward and land at $3.9bn / $7.3bn / $4.1bn / $5.2bn / $6.5bn for FY2021-25. The FY2026E figure is a judgement input. This is the single largest modelled rather than reported number in the workbook.
A24: 2. Depreciation is tagged 'Depreciation', not 'DepreciationDepletionAndAmortization'. | B24: Amortisation of acquisition-related intangibles is therefore excluded from the D&A used in the cash flow statement, EBITDA and the DCF. For TI in these years the difference is small, but EBITDA is understated to that extent and it is an assumption, not a fact.
A25: 3. Operating income does not tie to gross profit less R&D and SG&A. | B25: Residuals of +$196m, +$257m, $0m, -$124m and +$117m for FY2021-25 are restructuring and acquisition charges, which the extract does not tag. Note FY2024 is a net CREDIT. Carried as an explicit 'other operating' line and set to zero in the forecast.
A26: 4. Pre-tax income does not tie to operating income less interest expense. | B26: Residuals of $143m to $496m are 'other income/(expense), net', mostly interest income on the investment portfolio. Carried as an explicit line and forecast off the cash and investment balance.
A27: 5. Only capex is available in investing activities. | B27: The historical investing line is a derived plug that forces cash to tie to the reported balance sheet, so it also absorbs movements in the short-term investment portfolio. Historical investing and financing totals in this workbook are NOT as-reported figures.
A28: 6. Four balance sheet lines are residuals, not tagged values. | B28: Short-term investments and other current assets; goodwill, intangibles and other long-term assets; other current liabilities; other long-term liabilities. Each is backed out from a reported subtotal. All four are held flat across the forecast.
A29: 7. Short-term debt is the current portion of long-term debt only. | B29: The tag is LongTermDebtCurrent. Any commercial paper or revolver would not appear. Total debt shown here may understate gross borrowings.
A30: 8. The effective tax rate is 12.0%-12.9%, well below the 21% statutory rate. | B30: Driven by FDII and R&D credits. Forecast at 14.0%. Holding the historical rate would add roughly $6 per share; normalising to 18% would remove roughly $10.
A31: 9. Share count is the weighted-average diluted count, not the period-end count. | B31: Used in the DCF per-share bridge because a period-end count is not in the extract. Minor, but it is a mismatch of convention.
A32: 10. No share price anywhere in the extract. | B32: The upside line on the DCF tab stays blank until a live price is typed into the yellow cell.
A33: 11. FY2021 and FY2022 figures come from earlier filings than FY2023-25. | B33: FY2021 income statement data is from the FY2023 10-K and FY2022 from the FY2024 10-K, while FY2023-25 all come from the FY2025 10-K (accession 0000097476-26-000059, filed 2026-02-06). The extract keeps the latest-filed value for each period, so these reflect any restatement. All internal consistency tests still pass.

Sheet Source Data
A1: Texas Instruments Incorporated — Source Data Extract
A2: SEC XBRL company facts, CIK 97476. All figures $ in millions as reported. Every value on this tab is a hardcoded input (blue) taken directly from the JSON extract; no value on this tab is derived.
A3: Source file: lab05_financials.json | All FY2025/FY2024/FY2023 facts sourced from the FY2025 Form 10-K, accession 0000097476-26-000059, filed 2026-02-06.
A5: ($ in millions, except per-share) | B5: FY2021A | C5: FY2022A | D5: FY2023A | E5: FY2024A | F5: FY2025A | G5: FY2026E | H5: FY2027E | I5: FY2028E | J5: FY2029E | K5: FY2030E | M5: Notes / source
A6: INCOME STATEMENT
A7: Revenue | B7: 18344 | C7: 20028 | D7: 17519 | E7: 15641 | F7: 17682 | M7: RevenueFromContractWithCustomerExcludingAssessedTax
A8: Cost of revenue | B8: 5968 | C8: 6257 | D8: 6500 | E8: 6547 | F8: 7599 | M8: CostOfGoodsAndServicesSold
A9: Gross profit | B9: 12376 | C9: 13771 | D9: 11019 | E9: 9094 | F9: 10083 | M9: GrossProfit
A10: Research and development | B10: 1554 | C10: 1670 | D10: 1863 | E10: 1959 | F10: 2083 | M10: ResearchAndDevelopmentExpense
A11: Selling, general and administrative | B11: 1666 | C11: 1704 | D11: 1825 | E11: 1794 | F11: 1860 | M11: SellingGeneralAndAdministrativeExpense
A12: Operating income | B12: 8960 | C12: 10140 | D12: 7331 | E12: 5465 | F12: 6023 | M12: OperatingIncomeLoss
A13: Interest and debt expense | B13: 184 | C13: 214 | D13: 353 | E13: 508 | F13: 543 | M13: InterestAndDebtExpense
A14: Pre-tax income | B14: 8919 | C14: 10032 | D14: 7418 | E14: 5453 | F14: 5710 | M14: IncomeLossFromContinuingOperationsBeforeIncomeTaxesExtraordinaryItemsNoncontrollingInterest | N14: Tag: IncomeLossFromContinuingOperationsBeforeIncomeTaxesExtraordinaryItemsNoncontrollingInterest
A15: Income tax expense | B15: 1150 | C15: 1283 | D15: 908 | E15: 654 | F15: 709 | M15: IncomeTaxExpenseBenefit
A16: Net income | B16: 7769 | C16: 8749 | D16: 6510 | E16: 4799 | F16: 5001 | M16: NetIncomeLoss
A17: Diluted weighted-average shares (mm) | B17: 936 | C17: 926 | D17: 916 | E17: 919 | F17: 913 | M17: WeightedAverageNumberOfDilutedSharesOutstanding | N17: Weighted-average DILUTED shares. Used for EPS and for the DCF per-share bridge (period-end count not in extract).
A18: CASH FLOW
A19: Depreciation | B19: 755 | C19: 925 | D19: 1175 | E19: 1508 | F19: 1918 | M19: Depreciation | N19: TAG RISK: XBRL tag is 'Depreciation', NOT 'DepreciationDepletionAndAmortization'. Excludes amortisation of acquisition-related intangibles. Used as total D&A throughout.
A20: Capital expenditure | B20: 2462 | C20: 2797 | D20: 5071 | E20: 4820 | F20: 4550 | M20: PaymentsToAcquirePropertyPlantAndEquipment | N20: PaymentsToAcquirePropertyPlantAndEquipment. Investing section otherwise absent from extract.
A21: Cash flow from operations | B21: 8756 | C21: 8720 | D21: 6420 | E21: 6318 | F21: 7153 | M21: NetCashProvidedByUsedInOperatingActivities | N21: Reported total CFO. No sub-components (stock comp, deferred tax, WC detail) in the extract.
A22: BALANCE SHEET
A23: Cash and cash equivalents | B23: 4631 | C23: 3050 | D23: 2964 | E23: 3200 | F23: 3225 | M23: CashAndCashEquivalentsAtCarryingValue
A24: Accounts receivable, net | B24: 1701 | C24: 1895 | D24: 1787 | E24: 1719 | F24: 1963 | M24: AccountsReceivableNetCurrent
A25: Inventory, net | B25: 1910 | C25: 2757 | D25: 3999 | E25: 4527 | F25: 4804 | M25: InventoryNet
A26: Total current assets | B26: 13685 | C26: 14021 | D26: 15122 | E26: 15026 | F26: 13750 | M26: AssetsCurrent
A27: Property, plant and equipment, net | B27: 5141 | C27: 6876 | D27: 9999 | E27: 11347 | F27: 12320 | M27: PropertyPlantAndEquipmentNet
A28: Total assets | B28: 24676 | C28: 27207 | D28: 32348 | E28: 35509 | F28: 34585 | M28: Assets
A29: Accounts payable | B29: 571 | C29: 851 | D29: 802 | E29: 820 | F29: 756 | M29: AccountsPayableCurrent
A30: Total current liabilities | B30: 2569 | C30: 2985 | D30: 3320 | E30: 3643 | F30: 3159 | M30: LiabilitiesCurrent
A31: Long-term debt, current portion | B31: 500 | C31: 500 | D31: 599 | E31: 750 | F31: 500 | M31: LongTermDebtCurrent | N31: Tag is 'LongTermDebtCurrent' = current portion of LT debt only. Sits inside total current liabilities. No separate commercial paper / revolver line in the extract.
A32: Long-term debt, non-current | B32: 7241 | C32: 8235 | D32: 10624 | E32: 12846 | F32: 13548 | M32: LongTermDebtNoncurrent
A33: Total liabilities | B33: 11343 | C33: 12630 | D33: 15451 | E33: 18606 | F33: 18312 | M33: Liabilities
A34: Total stockholders equity | B34: 13333 | C34: 14577 | D34: 16897 | E34: 16903 | F34: 16273 | M34: StockholdersEquity
A36: FY2020 OPENING BALANCES (needed for the FY2021 roll-forwards)
B37: FY2020A
A38: Cash and cash equivalents | B38: 3107 | M38: FY2020 balances from the same companyfacts extract (2020-12-31 period end).
A39: Accounts receivable, net | B39: 1414
A40: Inventory, net | B40: 1955
A41: Accounts payable | B41: 415
A42: Property, plant and equipment, net | B42: 3269
A43: Long-term debt, non-current | B43: 6248
A44: Long-term debt, current portion | B44: 550
A45: Total stockholders equity | B45: 9187
